Workbook

Sheet Sheet3
A1: ticker | B1: BID | C1: CTG | D1: VCB | E1: HDB | F1: MBB | G1: TCB | H1: VPB | I1: ACB | J1: MSB | K1: STB | L1: TPB | M1: VIB | N1: EIB | O1: NAB | P1: OCB | Q1: SHB | R1: SSI | S1: HCM | T1: VCI | U1: DXG | V1: KDH | W1: NLG | X1: PDR | Y1: VHM | Z1: VRE | AA1: DPG | AB1: IDC | AC1: LHG | AD1: PHR | AE1: SZC | AF1: SIP | AG1: DPR | AH1: KBC | AI1: PLC | AJ1: DGC | AK1: CSV | AL1: DCM | AM1: DPM | AN1: DDV | AO1: DRC | AP1: CSM | AQ1: BSR | AR1: PVD | AS1: GEX | AT1: BWE | AU1: DHC | AV1: HDG | AW1: NT2 | AX1: QTP | AY1: PC1 | AZ1: POW | BA1: REE | BB1: VEA | BC1: VGC | BD1: PVS | BE1: GAS | BF1: PVB | BG1: HPG | BH1: HSG | BI1: NKG | BJ1: NTP | BK1: CTD | BL1: BMP | BM1: BAF | BN1: DBC | BO1: DGW | BP1: FRT | BQ1: MSN | BR1: MWG | BS1: PNJ | BT1: VNM | BU1: HAH | BV1: ANV | BW1: CTR | BX1: ELC | BY1: FPT | BZ1: MSH | CA1: TNG | CB1: VHC | CC1: HVN | CD1: PTB | CE1: PVT | CF1: GMD | CG1: HT1 | CH1: LCG | CI1: C4G | CJ1: HHV | CK1: VCG | CL1: TCH
A2: Rating | B2: BUY | C2: BUY | D2: BUY | E2: BUY | F2: BUY | G2: BUY | H2: BUY | I2: BUY | J2: HOLD | K2: HOLD | L2: HOLD | M2: BUY | N2: HOLD | O2: HOLD | P2: HOLD | Q2: HOLD | R2: BUY | S2: BUY | T2: HOLD | U2: BUY | V2: BUY | W2: BUY | X2: BUY | Y2: BUY | Z2: BUY | AA2: BUY | AB2: HOLD | AC2: NA | AD2: HOLD | AE2: BUY | AF2: NA | AG2: HOLD | AH2: NA | AI2: HOLD | AJ2: HOLD | AK2: HOLD | AL2: BUY | AM2: HOLD | AN2: BUY | AO2: HOLD | AP2: HOLD | AQ2: HOLD | AR2: BUY | AS2: HOLD | AT2: HOLD | AU2: BUY | AV2: BUY | AW2: HOLD | AX2: BUY | AY2: BUY | AZ2: BUY | BA2: HOLD | BB2: HOLD | BC2: HOLD | BD2: BUY | BE2: BUY | BF2: BUY | BG2: BUY | BH2: HOLD | BI2: HOLD | BJ2: HOLD | BK2: BUY | BL2: HOLD | BM2: NA | BN2: BUY | BO2: HOLD | BP2: BUY | BQ2: BUY | BR2: BUY | BS2: HOLD | BT2: BUY | BU2: BUY | BV2: BUY | BW2: HOLD | BX2: BUY | BY2: HOLD | BZ2: HOLD | CA2: HOLD | CB2: HOLD | CC2: BUY | CD2: BUY | CE2: HOLD | CF2: BUY | CG2: BUY | CH2: BUY | CI2: HOLD | CJ2: BUY | CK2: BUY | CL2: NA
A3: target_price | B3: 45000 | C3: 52500 | D3: 76000 | E3: 31000 | F3: 33000 | G3: 42000 | H3: 27000 | I3: 26400 | J3: 14000 | K3: 49000 | L3: 15500 | M3: 22200 | N3: 25200 | O3: 19500 | P3: 13900 | Q3: 20100 | R3: 31200 | S3: 28000 | T3: 42500 | U3: 21900 | V3: 39900 | W3: 44400 | X3: 23600 | Y3: 92500 | Z3: 31500 | AA3: 53000 | AB3: 65300 | AC3: 47300 | AD3: 64800 | AE3: 45000 | AF3: 0 | AG3: 49700 | AH3: 35000 | AI3: 0 | AJ3: 109300 | AK3: 0 | AL3: 47300 | AM3: 30500 | AN3: 38200 | AO3: 0 | AP3: 13500 | AQ3: 20100 | AR3: 23700 | AS3: 35100 | AT3: 42100 | AU3: 35100 | AV3: 33100 | AW3: 25300 | AX3: 12900 | AY3: 26700 | AZ3: 17700 | BA3: 67300 | BB3: 41500 | BC3: 46100 | BD3: 38600 | BE3: 80200 | BF3: 38700 | BG3: 32300 | BH3: 19900 | BI3: 14400 | BJ3: 66000 | BK3: 96200 | BL3: 151200 | BM3: 0 | BN3: 32200 | BO3: 52900 | BP3: 171300 | BQ3: 92700 | BR3: 84700 | BS3: 83000 | BT3: 64600 | BU3: 61700 | BV3: 36000 | BW3: 111000 | BX3: 28000 | BY3: 118700 | BZ3: 50600 | CA3: 23900 | CB3: 60000 | CC3: 39000 | CD3: 62706 | CE3: 19100 | CF3: 74900 | CG3: 14300 | CH3: 11500 | CI3: 9600 | CJ3: 15600 | CK3: 26100 | CL3: 22400
A4: 2025_rev | B4: 86855.1 | C4: 92204.892 | D4: 74171.354 | E4: 40259.7 | F4: 65788.201 | G4: 54304.021 | H4: 70386.133 | I4: 37297.512 | J4: 15880.374 | K4: 32623.844 | L4: 19423.168 | M4: 22804.392 | N4: 9980.2664 | O4: 10350.99 | P4: 11346.648 | Q4: 29629.843 | R4: 9571 | S4: 4864.38 | T4: 4472 | U4: 3146.8479 | V4: 4540 | W4: 7061 | X4: 4474 | Y4: 125810 | Z4: 9218.1678 | AA4: 4596 | AB4: 7351.7871 | AC4: 622 | AD4: 1645.8422 | AE4: 1670.2676 | AF4: 7479.2023 | AG4: 1334.8685 | AH4: 5949.2776 | AI4: 7261.0115 | AJ4: 10871.374 | AK4: 1987 | AL4: 19929.562 | AM4: 17284.032 | AN4: 5696.7889 | AO4: 4803.5805 | AP4: 4799.7848 | AQ4: 109209 | AR4: 8963 | AS4: 38136.903 | AT4: 4262.7199 | AU4: 3624.3448 | AV4: 3200.3596 | AW4: 7381.2259 | AX4: 12106.81 | AY4: 12788.225 | AZ4: 41988.326 | BA4: 10132.351 | BB4: 4321.0147 | BC4: 12419.734 | BD4: 36151 | BE4: 108710 | BF4: 480 | BG4: 173016.07 | BH4: 37911.723 | BI4: 16996.155 | BJ4: 6448.4827 | BK4: 24866.699 | BL4: 5654.208 | BM4: 4962 | BN4: 15152 | BO4: 24678 | BP4: 49315 | BQ4: 79506 | BR4: 153559 | BS4: 31700 | BT4: 63188 | BU4: 4727 | BV4: 5928 | BW4: 13957 | BX4: 1658 | BY4: 73267 | BZ4: 5838 | CA4: 8350 | CB4: 12518 | CC4: 118364 | CD4: 7123 | CE4: 13352 | CF4: 5166 | CG4: 7189 | CH4: 3219 | CI4: 3288 | CJ4: 3494.3677 | CK4: 14635 | CL4: 3963
A5: 2026_rev | B5: 100748.43 | C5: 105994.33 | D5: 85650.802 | E5: 49782.05 | F5: 82056.214 | G5: 65366.62 | H5: 83310.406 | I5: 42675.061 | J5: 18011.717 | K5: 37000.294 | L5: 21759.822 | M5: 26838.704 | N5: 11529.371 | O5: 11753.209 | P5: 13116.431 | Q5: 35349.625 | R5: 10815 | S5: 5788.61 | T5: 5321.68 | U5: 18030.777 | V5: 4637 | W5: 8518 | X5: 6101 | Y5: 115136 | Z5: 10941 | AA5: 5253 | AB5: 7572.3407 | AC5: 0 | AD5: 1834.8719 | AE5: 1743.6866 | AF5: 7703.5783 | AG5: 1385.4156 | AH5: 14924.701 | AI5: 7392.4131 | AJ5: 12202.871 | AK5: 2086.35 | AL5: 19723.883 | AM5: 17273.084 | AN5: 5141.5633 | AO5: 5052.3286 | AP5: 4903.4517 | AQ5: 140582 | AR5: 9983 | AS5: 38892.552 | AT5: 4555.3088 | AU5: 3714.0387 | AV5: 3675.3972 | AW5: 7559.6851 | AX5: 12129.313 | AY5: 14525.777 | AZ5: 60550.125 | BA5: 12098.999 | BB5: 4387.8945 | BC5: 12210.714 | BD5: 43138 | BE5: 119613 | BF5: 1510 | BG5: 217293.39 | BH5: 39852.355 | BI5: 29707.736 | BJ5: 7093.331 | BK5: 29750 | BL5: 5908.6474 | BM5: 5537 | BN5: 16823 | BO5: 27682 | BP5: 57754 | BQ5: 86215 | BR5: 172781 | BS5: 33514 | BT5: 66202 | BU5: 5196 | BV5: 6474 | BW5: 15684 | BX5: 1744 | BY5: 86654 | BZ5: 6340 | CA5: 9177 | CB5: 14226 | CC5: 130924 | CD5: 7767 | CE5: 13545 | CF5: 5636 | CG5: 7631 | CH5: 2292 | CI5: 3376 | CJ5: 3536.5317 | CK5: 17020 | CL5: 6617
A6: 2025_npat | B6: 26773.327 | C6: 29994.821 | D6: 35307.008 | E6: 15580.847 | F6: 25355.979 | G6: 24829.701 | H6: 18274.466 | I6: 18939.743 | J6: 6436.1291 | K6: 11837.217 | L6: 6816.0784 | M6: 8744.8515 | N6: 4062.3505 | O6: 4165 | P6: 3887.0189 | Q6: 15995.427 | R6: 3285.765 | S6: 1175.855 | T6: 1386 | U6: 223.5037 | V6: 811 | W6: 634 | X6: 641 | Y6: 36602 | Z6: 4413 | AA6: 270 | AB6: 1652.981 | AC6: 260 | AD6: 540.41102 | AE6: 661.77403 | AF6: 1324.4627 | AG6: 290.58575 | AH6: 1352.2906 | AI6: 118.5371 | AJ6: 3488.3822 | AK6: 247 | AL6: 2845.4463 | AM6: 1381.333 | AN6: 485.61948 | AO6: 108.71932 | AP6: 73.001339 | AQ6: 1196 | AR6: 710 | AS6: 1129.6703 | AT6: 695.96081 | AU6: 308.74048 | AV6: 882.56169 | AW6: 528.85739 | AX6: 783.61944 | AY6: 559.2402 | AZ6: 1562.5086 | BA6: 2486.9169 | BB6: 7293.4831 | BC6: 1109.826 | BD6: 1177 | BE6: 13131 | BF6: 56 | BG6: 15816.642 | BH6: 740.81612 | BI6: 300.58269 | BJ6: 957.08259 | BK6: 453.83784 | BL6: 1237.4429 | BM6: 525 | BN6: 1643 | BO6: 530 | BP6: 610 | BQ6: 3435 | BR6: 5800 | BS6: 2074 | BT6: 9144 | BU6: 774 | BV6: 955 | BW6: 566 | BX6: 143 | BY6: 9332 | BZ6: 440 | CA6: 342 | CB6: 1250 | CC6: 8956 | CD6: 524 | CE6: 1071 | CF6: 1452 | CG6: 216 | CH6: 153 | CI6: 203 | CJ6: 497.62231 | CK6: 885 | CL6: 997
A7: 2026_npat | B7: 31143.59 | C7: 36534.267 | D7: 41707.746 | E7: 19865.033 | F7: 30675.762 | G7: 30000.567 | H7: 21970.001 | I7: 21965.66 | J7: 7496.3334 | K7: 13648.491 | L7: 7932.9675 | M7: 10812.779 | N7: 4734.7519 | O7: 4715.6641 | P7: 4501.5981 | Q7: 19408.209 | R7: 3791.77 | S7: 1376.9267 | T7: 1630 | U7: 2673.3262 | V7: 1003 | W7: 1200 | X7: 1410 | Y7: 39843 | Z7: 5355 | AA7: 376 | AB7: 1891.7298 | AC7: 0 | AD7: 576.01554 | AE7: 759.69736 | AF7: 1348.164 | AG7: 317.98512 | AH7: 5371.3018 | AI7: 125.51367 | AJ7: 3865.038 | AK7: 266.76 | AL7: 2621.1106 | AM7: 1120.5364 | AN7: 476.58296 | AO7: 191.47113 | AP7: 93.42625 | AQ7: 1293 | AR7: 883 | AS7: 1292.1494 | AT7: 884 | AU7: 322.13148 | AV7: 1337.736 | AW7: 724.74411 | AX7: 724.08522 | AY7: 1157.3368 | AZ7: 2122.3378 | BA7: 3043 | BB7: 7444.501 | BC7: 1068.29 | BD7: 1061 | BE7: 12278 | BF7: 163 | BG7: 22693.427 | BH7: 705.14803 | BI7: 256.00341 | BJ7: 1070.982 | BK7: 433.18357 | BL7: 1126.2411 | BM7: 561 | BN7: 1763 | BO7: 644 | BP7: 865 | BQ7: 4216 | BR7: 6841 | BS7: 2229 | BT7: 9597 | BU7: 891 | BV7: 1136 | BW7: 762 | BX7: 164 | BY7: 11219 | BZ7: 501 | CA7: 378 | CB7: 1477 | CC7: 9505 | CD7: 583 | CE7: 1121 | CF7: 1545 | CG7: 306 | CH7: 62 | CI7: 209 | CJ7: 675.30407 | CK7: 1218 | CL7: 2358
A8: 2025_eps | B8: 3760.9871 | C8: 5585.6364 | D8: 4225.5041 | E8: 3712.2984 | F8: 3613.177 | G8: 3511.8801 | H8: 2303.3396 | I8: 4240.2492 | J8: 2475.4343 | K8: 6278.972 | L8: 2579.9362 | M8: 2935.3731 | N8: 2173.7626 | O8: 3149 | P8: 1576.3793 | Q8: 3294.5869 | R8: 1654 | S8: 1342.857 | T8: 1948 | U8: 309.36869 | V8: 756 | W8: 1580 | X8: 716 | Y8: 8893 | Z8: 1895 | AA8: 4263 | AB8: 5009.0332 | AC8: 5194 | AD8: 3988.2968 | AE8: 3676.5228 | AF8: 14570.546 | AG8: 3344.4511 | AH8: 1761.7017 | AI8: 1445.9693 | AJ8: 9185.2882 | AK8: 2235.2959 | AL8: 4031.1385 | AM8: 1905.1342 | AN8: 3323.659 | AO8: 648.81072 | AP8: 520.63913 | AQ8: 386 | AR8: 1265 | AS8: 1314.4872 | AT8: 3164.8968 | AU8: 3196.0712 | AV8: 2624.3286 | AW8: 1837.1012 | AX8: 1741.3765 | AY8: 1563.8708 | AZ8: 667.22548 | BA8: 5279.4188 | BB8: 5488.7742 | BC8: 2475.0803 | BD8: 1847 | BE8: 5605 | BF8: 2464 | BG8: 2472.7938 | BH8: 1192.9746 | BI8: 671.58678 | BJ8: 6064.5022 | BK8: 4541.5569 | BL8: 15116.403 | BM8: 2108 | BN8: 3634 | BO8: 2418 | BP8: 4481 | BQ8: 2270 | BR8: 3909 | BS8: 5532 | BT8: 3916 | BU8: 6379 | BV8: 3588 | BW8: 4948 | BX8: 1740 | BY8: 5042 | BZ8: 5861 | CA8: 2812 | CB8: 5682 | CC8: 2873 | CD8: 7838 | CE8: 2119 | CF8: 3458 | CG8: 747 | CH8: 773 | CI8: 567 | CJ8: 1151.2225 | CK8: 1478 | CL8: 1492
A9: 2026_eps | B9: 4202.5156 | C9: 5803.9342 | D9: 4991.5373 | E9: 3941.8475 | F9: 4371.2356 | G9: 4233.6299 | H9: 2769.13 | I9: 4917.6947 | J9: 2883.2052 | K9: 7239.7505 | L9: 3002.687 | M9: 3629.5117 | N9: 2533.5643 | O9: 3565.5833 | P9: 1825.6217 | Q9: 3997.5196 | R9: 2348 | S9: 1574 | T9: 2280 | U9: 3700.3569 | V9: 935 | W9: 2991 | X9: 1574 | Y9: 9681 | Z9: 2299 | AA9: 5926 | AB9: 5732.5144 | AC9: 0 | AD9: 4251.0624 | AE9: 4220.5414 | AF9: 14831.287 | AG9: 3659.7999 | AH9: 6997.4837 | AI9: 1552.5218 | AJ9: 10177.064 | AK9: 2414.1196 | AL9: 3713.3226 | AM9: 1705.5138 | AN9: 3261.8116 | AO9: 1142.6536 | AP9: 666.3078 | AQ9: 417 | AR9: 1484 | AS9: 1503.5483 | AT9: 4097.2114 | AU9: 3334.6944 | AV9: 3977.8055 | AW9: 2517.5563 | AX9: 1609.0783 | AY9: 3236.4004 | AZ9: 906.28481 | BA9: 6556.7218 | BB9: 5602.424 | BC9: 2382.4488 | BD9: 1665 | BE9: 5241 | BF9: 7175 | BG9: 3547.9189 | BH9: 1135.5364 | BI9: 571.98406 | BJ9: 7513.9611 | BK9: 4334.8695 | BL9: 13757.979 | BM9: 2247 | BN9: 3898 | BO9: 2938 | BP9: 6350 | BQ9: 2787 | BR9: 4611 | BS9: 6072 | BT9: 4110 | BU9: 7340 | BV9: 4266 | BW9: 6659 | BX9: 1999 | BY9: 6061 | BZ9: 6684 | CA9: 3104 | CB9: 6713 | CC9: 3236 | CD9: 8712 | CE9: 2207 | CF9: 3678 | CG9: 1072 | CH9: 321 | CI9: 585 | CJ9: 1562.2798 | CK9: 2035 | CL9: 3528
A10: 2025_bv | B10: 26098.276 | C10: 33059.418 | D10: 27696.082 | E10: 16695.368 | F10: 19159.363 | G10: 23110.798 | H10: 19689.244 | I10: 21692.616 | J10: 15965 | K10: 33615.288 | L10: 15483.398 | M10: 16421.647 | N10: 14943.831 | O10: 17760 | P10: 13938.603 | Q10: 16990.255 | R10: 19800 | S10: 16084.59 | T10: 20053 | U10: 15504.364 | V10: 18054 | W10: 26730 | X10: 13751 | Y10: 57975 | Z10: 19897 | AA10: 34618 | AB10: 27766.102 | AC10: 37432 | AD10: 27756.872 | AE10: 22650.295 | AF10: 49349.294 | AG10: 27521.624 | AH10: 29131.542 | AI10: 14917.599 | AJ10: 42822.955 | AK10: 14063.51 | AL10: 22175.856 | AM10: 22340.519 | AN10: 12232.17 | AO10: 15519.442 | AP10: 13922.444 | AQ10: 19100 | AR10: 28700 | AS10: 29923.46 | AT10: 27805.355 | AU10: 22388.618 | AV10: 25150.473 | AW10: 17388.761 | AX10: 11500 | AY10: 23760.341 | AZ10: 15512.888 | BA10: 54200.079 | BB10: 19802.284 | BC10: 24110.108 | BD10: 27850 | BE10: 26696 | BF10: 21806 | BG10: 20395.985 | BH10: 18767.305 | BI10: 14378.208 | BJ10: 31528.867 | BK10: 89690.771 | BL10: 36119.934 | BM10: 14680 | BN10: 24637 | BO10: 15747 | BP10: 18520 | BQ10: 22258 | BR10: 22026 | BS10: 36614 | BT10: 17911 | BU10: 32179 | BV10: 13256 | BW10: 27219 | BX10: 17364 | BY10: 21041 | BZ10: 29592 | CA10: 17259 | CB10: 48739 | CC10: 1230 | CD10: 55667 | CE10: 25830 | CF10: 34618 | CG10: 13404 | CH10: 13672 | CI10: 11543 | CJ10: 22518.842 | CK10: 20023 | CL10: 15564
A11: 2026_bv | B11: 29272.438 | C11: 34006.648 | D11: 36959.264 | E11: 17846.327 | F11: 23530.599 | G11: 26591.298 | H11: 21458.374 | I11: 25084.816 | J11: 18390.925 | K11: 37752.746 | L11: 17011.735 | M11: 19298.312 | N11: 16791.529 | O11: 21389.377 | P11: 15278.525 | Q11: 19790.654 | R11: 22084 | S11: 17655.59 | T11: 22331.63 | U11: 19204.721 | V11: 19095 | W11: 29846 | X11: 15366 | Y11: 67675 | Z11: 22196 | AA11: 39580 | AB11: 33498.616 | AC11: 0 | AD11: 29007.934 | AE11: 26870.836 | AF11: 55180.171 | AG11: 28181.424 | AH11: 36867.485 | AI11: 14470.121 | AJ11: 50645.073 | AK11: 14204.145 | AL11: 25128.718 | AM11: 21949.592 | AN11: 15065.588 | AO11: 16266.178 | AP11: 14568.864 | AQ11: 20300 | AR11: 29200 | AS11: 32823.469 | AT11: 31300.401 | AU11: 25723.312 | AV11: 29813.373 | AW11: 21406.286 | AX11: 11700 | AY11: 27864.524 | AZ11: 16573.314 | BA11: 62262.309 | BB11: 19860.106 | BC11: 26754.251 | BD11: 30060 | BE11: 27887 | BF11: 28900 | BG11: 23942.561 | BH11: 19906.005 | BI11: 14950.192 | BJ11: 38133.734 | BK11: 94012.643 | BL11: 36877.913 | BM11: 16411 | BN11: 29378 | BO11: 18488 | BP11: 24878 | BQ11: 25042 | BR11: 25670 | BS11: 40695 | BT11: 18543 | BU11: 38775 | BV11: 16529 | BW11: 33878 | BX11: 19545 | BY11: 25579 | BZ11: 32565 | CA11: 19132 | CB11: 54571 | CC11: 3179 | CD11: 64433 | CE11: 28653 | CF11: 36923 | CG11: 13970 | CH11: 13734 | CI11: 12126 | CJ11: 24286.442 | CK11: 22022 | CL11: 18392
A12: 2025_roe | B12: 0.16452466 | C12: 0.18454787 | D12: 0.1651663 | E12: 0.25016804 | F12: 0.20564273 | G12: 0.16080519 | H12: 0.1225991 | I12: 0.21002716 | J12: 0.16434091 | K12: 0.20004736 | L12: 0.17365192 | M12: 0.19265184 | N12: 0.15321936 | O12: 0.195 | P12: 0.1177147 | Q12: 0.20629553 | R12: 0.117 | S12: 0.115 | T12: 0.101 | U12: 0.022910025 | V12: 0.067 | W12: 0.069 | X12: 0.068 | Y12: 0.143 | Z12: 0.095 | AA12: 0.122 | AB12: 0.1598079 | AC12: 0.1388 | AD12: 0.13753907 | AE12: 0.16231677 | AF12: 0 | AG12: 0.093872926 | AH12: 0.060474029 | AI12: 0.096930432 | AJ12: 0.24761975 | AK12: 0.15894296 | AL12: 0.24229828 | AM12: 0.090927708 | AN12: 0.21240671 | AO12: 0.044973208 | AP12: 0.050599317 | AQ12: 0.08 | AR12: 0.06 | AS12: 0.089012451 | AT12: 0.1239787 | AU12: 0.14822838 | AV12: 0.13494248 | AW12: 0.11503292 | AX12: 0.15244596 | AY12: 0.096304461 | AZ12: 0.052331989 | BA12: 0.12821127 | BB12: 0.28044071 | BC12: 0.12437947 | BD12: 0.09 | BE12: 0.18 | BF12: 0.11 | BG12: 0.12123924 | BH12: 0.063569697 | BI12: 0.046708658 | BJ12: 0.2129746 | BK12: 0.050635721 | BL12: 0.41850583 | BM12: 0.103 | BN12: 0.19 | BO12: 0.15 | BP12: 0.24 | BQ12: 0.12 | BR12: 0.177 | BS12: 0.17 | BT12: 0.26 | BU12: 0.16 | BV12: 0.26 | BW12: 0.18 | BX12: 0.1 | BY12: 0.21 | BZ12: 0.2 | CA12: 0.17455746 | CB12: 0.12 | CD12: 0.14 | CE12: 0.116 | CF12: 0.13 | CG12: 0.04 | CH12: 0.06 | CI12: 0.05 | CJ12: 0.051122634 | CK12: 0.07 | CL12: 0.082
A13: 2026_roe | B13: 0.15466813 | C13: 0.18659359 | D13: 0.15440447 | E13: 0.24829904 | F13: 0.20478986 | G13: 0.17053982 | H13: 0.13459491 | I13: 0.21025929 | J13: 0.16784326 | K13: 0.20288496 | L13: 0.18480841 | M13: 0.20322037 | N13: 0.15966823 | O13: 0.18215262 | P13: 0.12496928 | Q13: 0.21736927 | R13: 0.124 | S13: 0.123 | T13: 0.116 | U13: 0.21508707 | V13: 0.058 | W13: 0.101 | X13: 0.136 | Y13: 0.137 | Z13: 0.104 | AA13: 1.433 | AB13: 0.15461271 | AC13: 0 | AD13: 0.1405374 | AE13: 0.15706773 | AF13: 0 | AG13: 0.10085641 | AH13: 0.18980095 | AI13: 0.10729156 | AJ13: 0.23153104 | AK13: 0.16995881 | AL13: 0.19697508 | AM13: 0.07507419 | AN13: 0.19266528 | AO13: 0.075598331 | AP13: 0.061883167 | AQ13: 0.08 | AR13: 0.06 | AS13: 0.095088397 | AT13: 0.14248695 | AU13: 0.15917111 | AV13: 0.17485763 | AW13: 0.12978751 | AX13: 0.13873591 | AY13: 0.15900027 | AZ13: 0.066098564 | BA13: 0.13845208 | BB13: 0.28542133 | BC13: 0.10396839 | BD13: 0.08 | BE13: 0.16 | BF13: 0.28 | BG13: 0.1481846 | BH13: 0.057047797 | BI13: 0.038253596 | BJ13: 0.19704236 | BK13: 0.046109432 | BL13: 0.37306827 | BM13: 0.106 | BN13: 0.18 | BO13: 0.16 | BP13: 0.26 | BQ13: 0.14 | BR13: 0.18 | BS13: 0.17 | BT13: 0.25 | BU13: 0.15 | BV13: 0.27 | BW13: 0.2 | BX13: 0.1 | BY13: 0.21 | BZ13: 0.19 | CA13: 0.15 | CB13: 0.12 | CD13: 0.14 | CE13: 0.105 | CF13: 0.13 | CG13: 0.06 | CH13: 0.02 | CI13: 0.049 | CJ13: 0.06432724 | CK13: 0.09 | CL13: 0.145
A14: 2025_roa | B14: 0.0089920402 | C14: 0.011769472 | D14: 0.015613357 | E14: 0.019724712 | F14: 0.019689728 | G14: 0.023218685 | H14: 0.018052079 | I14: 0.020531521 | J14: 0.018940011 | K14: 0.014979945 | L14: 0.01568287 | M14: 0.016421619 | N14: 0.015917963 | O14: 0.016 | P14: 0.012843388 | Q14: 0.01600333 | R14: 0.048 | S14: 0.046 | T14: 0.048 | U14: 0.011452492 | V14: 0.042 | W14: 0.037 | X14: 0.033 | Y14: 0.059 | Z14: 0.076 | AA14: 0.047 | AB14: 0.080242595 | AC14: 0.0767 | AD14: 0.0786555 | AE14: 0.06441227 | AF14: 0 | AG14: 0.059594156 | AH14: 0.034925544 | AI14: 0.023314333 | AJ14: 0.21775575 | AK14: 0.13286713 | AL14: 0.16807406 | AM14: 0.069828445 | AN14: 0.27171459 | AO14: 0.025495719 | AP14: 0.037447404 | AQ14: 0.05 | AR14: 0.041 | AS14: 0.045397963 | AT14: 0.050910362 | AU14: 0.088286099 | AV14: 0.076298339 | AW14: 0.055877451 | AX14: 0.10686118 | AY14: 0.03595861 | AZ14: 0.021695892 | BA14: 0.08300492 | BB14: 0.26691027 | BC14: 0.050983535 | BD14: 0.047 | BE14: 0.15 | BF14: 0.03 | BG14: 0.063580475 | BH14: 0.036596329 | BI14: 0.019066949 | BJ14: 0.12248285 | BK14: 0.01534117 | BL14: 0.34840588 | BM14: 0.045 | BN14: 0.1 | BO14: 0.06 | BP14: 0.03 | BQ14: 0.04 | BR14: 0.076 | BS14: 0.11 | BT14: 0.17 | BU14: 0.1 | BV14: 0.17 | BW14: 0.06 | BX14: 0.06 | BY14: 0.12 | BZ14: 0.11 | CA14: 0.05 | CB14: 0.08 | CC14: 0.12 | CD14: 0.081215969 | CE14: 0.059 | CF14: 0.09 | CG14: 0.02 | CH14: 0.03 | CI14: 0.021 | CJ14: 0.012850105 | CK14: 0.03 | CL14: 0.066
A15: 2026_roa | B15: 0.0090446045 | C15: 0.012658663 | D15: 0.015649895 | E15: 0.019989579 | F15: 0.018550651 | G15: 0.023451142 | H15: 0.017838786 | I15: 0.020800811 | J15: 0.01926098 | K15: 0.014481271 | L15: 0.015686145 | M15: 0.017479293 | N15: 0.015924709 | O15: 0.015555162 | P15: 0.012864721 | Q15: 0.017143565 | R15: 0.049 | S15: 0.049 | T15: 0.05 | U15: 0.079828726 | V15: 0.034 | W15: 0.049 | X15: 0.066 | Y15: 0.048 | Z15: 0.088 | AA15: 0.059 | AB15: 0.08029506 | AC15: 0 | AD15: 0.086016352 | AE15: 0.068991767 | AF15: 0 | AG15: 0.056648538 | AH15: 0.11364844 | AI15: 0.032362262 | AJ15: 0.20664111 | AK15: 0.1434965 | AL15: 0.13888075 | AM15: 0.048515527 | AN15: 0.21650742 | AO15: 0.043462167 | AP15: 0.043256938 | AQ15: 0.05 | AR15: 0.04 | AS15: 0.044737672 | AT15: 0.065080959 | AU15: 0.083152035 | AV15: 0.097990445 | AW15: 0.067156397 | AX15: 0.098462112 | AY15: 0.066343784 | AZ15: 0.027015317 | BA15: 0.096570825 | BB15: 0.27156914 | BC15: 0.044888866 | BD15: 0.04 | BE15: 0.15 | BF15: 0.13 | BG15: 0.07601043 | BH15: 0.033242791 | BI15: 0.010993628 | BJ15: 0.11896107 | BK15: 0.013599236 | BL15: 0.30625167 | BM15: 0.048 | BN15: 0.1 | BO15: 0.06 | BP15: 0.04 | BQ15: 0.05 | BR15: 0.081 | BS15: 0.11 | BT15: 0.17 | BU15: 0.1 | BV15: 0.17 | BW15: 0.08 | BX15: 0.06 | BY15: 0.12 | BZ15: 0.11 | CA15: 0.05 | CB15: 0.09 | CC15: 0.12 | CD15: 0.08 | CE15: 0.057 | CF15: 0.1 | CG15: 0.03 | CH15: 0.02 | CI15: 0.021 | CJ15: 0.017356808 | CK15: 0.04 | CL15: 0.12

Sheet Codedata
A1: ticker | B1: =A_Entry_Forecast[[#Headers],[Rating]] -> Rating | C1: target_price | D1: 2025_rev | E1: 2026_rev | F1: 2025_npat | G1: 2026_npat | H1: 2025_eps | I1: 2026_eps | J1: 2025_bv | K1: 2026_bv | L1: 2025_roe | M1: 2026_roe | N1: 2025_roa | O1: 2026_roa
A2: =Rawdata!C8 -> BID | B2: =Rawdata!D8 -> BUY | C2: =Rawdata!E8 -> 45000 | D2: =Rawdata!F8 -> 86855.1 | E2: =Rawdata!G8 -> 100748.43 | F2: =Rawdata!I8 -> 26773.327 | G2: =Rawdata!J8 -> 31143.59 | H2: =Rawdata!L8 -> 3760.9871 | I2: =Rawdata!M8 -> 4202.5156 | J2: =Rawdata!O8 -> 26098.276 | K2: =Rawdata!P8 -> 29272.438 | L2: =Rawdata!U8 -> 0.16452466 | M2: =Rawdata!V8 -> 0.15466813 | N2: =Rawdata!R8 -> 0.0089920402 | O2: =Rawdata!S8 -> 0.0090446045
A3: =Rawdata!C9 -> CTG | B3: =Rawdata!D9 -> BUY | C3: =Rawdata!E9 -> 52500 | D3: =Rawdata!F9 -> 92204.892 | E3: =Rawdata!G9 -> 105994.33 | F3: =Rawdata!I9 -> 29994.821 | G3: =Rawdata!J9 -> 36534.267 | H3: =Rawdata!L9 -> 5585.6364 | I3: =Rawdata!M9 -> 5803.9342 | J3: =Rawdata!O9 -> 33059.418 | K3: =Rawdata!P9 -> 34006.648 | L3: =Rawdata!U9 -> 0.18454787 | M3: =Rawdata!V9 -> 0.18659359 | N3: =Rawdata!R9 -> 0.011769472 | O3: =Rawdata!S9 -> 0.012658663
A4: =Rawdata!C10 -> VCB | B4: =Rawdata!D10 -> BUY | C4: =Rawdata!E10 -> 76000 | D4: =Rawdata!F10 -> 74171.354 | E4: =Rawdata!G10 -> 85650.802 | F4: =Rawdata!I10 -> 35307.008 | G4: =Rawdata!J10 -> 41707.746 | H4: =Rawdata!L10 -> 4225.5041 | I4: =Rawdata!M10 -> 4991.5373 | J4: =Rawdata!O10 -> 27696.082 | K4: =Rawdata!P10 -> 36959.264 | L4: =Rawdata!U10 -> 0.1651663 | M4: =Rawdata!V10 -> 0.15440447 | N4: =Rawdata!R10 -> 0.015613357 | O4: =Rawdata!S10 -> 0.015649895
A5: =Rawdata!C11 -> HDB | B5: =Rawdata!D11 -> BUY | C5: =Rawdata!E11 -> 31000 | D5: =Rawdata!F11 -> 40259.7 | E5: =Rawdata!G11 -> 49782.05 | F5: =Rawdata!I11 -> 15580.847 | G5: =Rawdata!J11 -> 19865.033 | H5: =Rawdata!L11 -> 3712.2984 | I5: =Rawdata!M11 -> 3941.8475 | J5: =Rawdata!O11 -> 16695.368 | K5: =Rawdata!P11 -> 17846.327 | L5: =Rawdata!U11 -> 0.25016804 | M5: =Rawdata!V11 -> 0.24829904 | N5: =Rawdata!R11 -> 0.019724712 | O5: =Rawdata!S11 -> 0.019989579
A6: =Rawdata!C12 -> MBB | B6: =Rawdata!D12 -> BUY | C6: =Rawdata!E12 -> 33000 | D6: =Rawdata!F12 -> 65788.201 | E6: =Rawdata!G12 -> 82056.214 | F6: =Rawdata!I12 -> 25355.979 | G6: =Rawdata!J12 -> 30675.762 | H6: =Rawdata!L12 -> 3613.177 | I6: =Rawdata!M12 -> 4371.2356 | J6: =Rawdata!O12 -> 19159.363 | K6: =Rawdata!P12 -> 23530.599 | L6: =Rawdata!U12 -> 0.20564273 | M6: =Rawdata!V12 -> 0.20478986 | N6: =Rawdata!R12 -> 0.019689728 | O6: =Rawdata!S12 -> 0.018550651
A7: =Rawdata!C13 -> TCB | B7: =Rawdata!D13 -> BUY | C7: =Rawdata!E13 -> 42000 | D7: =Rawdata!F13 -> 54304.021 | E7: =Rawdata!G13 -> 65366.62 | F7: =Rawdata!I13 -> 24829.701 | G7: =Rawdata!J13 -> 30000.567 | H7: =Rawdata!L13 -> 3511.8801 | I7: =Rawdata!M13 -> 4233.6299 | J7: =Rawdata!O13 -> 23110.798 | K7: =Rawdata!P13 -> 26591.298 | L7: =Rawdata!U13 -> 0.16080519 | M7: =Rawdata!V13 -> 0.17053982 | N7: =Rawdata!R13 -> 0.023218685 | O7: =Rawdata!S13 -> 0.023451142
A8: =Rawdata!C14 -> VPB | B8: =Rawdata!D14 -> BUY | C8: =Rawdata!E14 -> 27000 | D8: =Rawdata!F14 -> 70386.133 | E8: =Rawdata!G14 -> 83310.406 | F8: =Rawdata!I14 -> 18274.466 | G8: =Rawdata!J14 -> 21970.001 | H8: =Rawdata!L14 -> 2303.3396 | I8: =Rawdata!M14 -> 2769.13 | J8: =Rawdata!O14 -> 19689.244 | K8: =Rawdata!P14 -> 21458.374 | L8: =Rawdata!U14 -> 0.1225991 | M8: =Rawdata!V14 -> 0.13459491 | N8: =Rawdata!R14 -> 0.018052079 | O8: =Rawdata!S14 -> 0.017838786
A9: =Rawdata!C15 -> ACB | B9: =Rawdata!D15 -> BUY | C9: =Rawdata!E15 -> 26400 | D9: =Rawdata!F15 -> 37297.512 | E9: =Rawdata!G15 -> 42675.061 | F9: =Rawdata!I15 -> 18939.743 | G9: =Rawdata!J15 -> 21965.66 | H9: =Rawdata!L15 -> 4240.2492 | I9: =Rawdata!M15 -> 4917.6947 | J9: =Rawdata!O15 -> 21692.616 | K9: =Rawdata!P15 -> 25084.816 | L9: =Rawdata!U15 -> 0.21002716 | M9: =Rawdata!V15 -> 0.21025929 | N9: =Rawdata!R15 -> 0.020531521 | O9: =Rawdata!S15 -> 0.020800811
A10: =Rawdata!C16 -> MSB | B10: =Rawdata!D16 -> HOLD | C10: =Rawdata!E16 -> 14000 | D10: =Rawdata!F16 -> 15880.374 | E10: =Rawdata!G16 -> 18011.717 | F10: =Rawdata!I16 -> 6436.1291 | G10: =Rawdata!J16 -> 7496.3334 | H10: =Rawdata!L16 -> 2475.4343 | I10: =Rawdata!M16 -> 2883.2052 | J10: =Rawdata!O16 -> 15965 | K10: =Rawdata!P16 -> 18390.925 | L10: =Rawdata!U16 -> 0.16434091 | M10: =Rawdata!V16 -> 0.16784326 | N10: =Rawdata!R16 -> 0.018940011 | O10: =Rawdata!S16 -> 0.01926098
A11: =Rawdata!C17 -> STB | B11: =Rawdata!D17 -> HOLD | C11: =Rawdata!E17 -> 49000 | D11: =Rawdata!F17 -> 32623.844 | E11: =Rawdata!G17 -> 37000.294 | F11: =Rawdata!I17 -> 11837.217 | G11: =Rawdata!J17 -> 13648.491 | H11: =Rawdata!L17 -> 6278.972 | I11: =Rawdata!M17 -> 7239.7505 | J11: =Rawdata!O17 -> 33615.288 | K11: =Rawdata!P17 -> 37752.746 | L11: =Rawdata!U17 -> 0.20004736 | M11: =Rawdata!V17 -> 0.20288496 | N11: =Rawdata!R17 -> 0.014979945 | O11: =Rawdata!S17 -> 0.014481271
A12: =Rawdata!C18 -> TPB | B12: =Rawdata!D18 -> HOLD | C12: =Rawdata!E18 -> 15500 | D12: =Rawdata!F18 -> 19423.168 | E12: =Rawdata!G18 -> 21759.822 | F12: =Rawdata!I18 -> 6816.0784 | G12: =Rawdata!J18 -> 7932.9675 | H12: =Rawdata!L18 -> 2579.9362 | I12: =Rawdata!M18 -> 3002.687 | J12: =Rawdata!O18 -> 15483.398 | K12: =Rawdata!P18 -> 17011.735 | L12: =Rawdata!U18 -> 0.17365192 | M12: =Rawdata!V18 -> 0.18480841 | N12: =Rawdata!R18 -> 0.01568287 | O12: =Rawdata!S18 -> 0.015686145
A13: =Rawdata!C19 -> VIB | B13: =Rawdata!D19 -> BUY | C13: =Rawdata!E19 -> 22200 | D13: =Rawdata!F19 -> 22804.392 | E13: =Rawdata!G19 -> 26838.704 | F13: =Rawdata!I19 -> 8744.8515 | G13: =Rawdata!J19 -> 10812.779 | H13: =Rawdata!L19 -> 2935.3731 | I13: =Rawdata!M19 -> 3629.5117 | J13: =Rawdata!O19 -> 16421.647 | K13: =Rawdata!P19 -> 19298.312 | L13: =Rawdata!U19 -> 0.19265184 | M13: =Rawdata!V19 -> 0.20322037 | N13: =Rawdata!R19 -> 0.016421619 | O13: =Rawdata!S19 -> 0.017479293
... A21: =Rawdata!C27 -> DXG | B21: =Rawdata!D27 -> BUY | C21: =Rawdata!E27 -> 21900 | D21: =Rawdata!F27 -> 3146.8479 | E21: =Rawdata!G27 -> 18030.777 | F21: =Rawdata!I27 -> 223.5037 | G21: =Rawdata!J27 -> 2673.3262 | H21: =Rawdata!L27 -> 309.36869 | I21: =Rawdata!M27 -> 3700.3569 | J21: =Rawdata!O27 -> 15504.364 | K21: =Rawdata!P27 -> 19204.721 | L21: =Rawdata!U27 -> 0.022910025 | M21: =Rawdata!V27 -> 0.21508707 | N21: =Rawdata!R27 -> 0.011452492 | O21: =Rawdata!S27 -> 0.079828726
A22: =Rawdata!C29 -> KDH | B22: =Rawdata!D29 -> BUY | C22: =Rawdata!E29 -> 39900 | D22: =Rawdata!F29 -> 4540 | E22: =Rawdata!G29 -> 4637 | F22: =Rawdata!I29 -> 811 | G22: =Rawdata!J29 -> 1003 | H22: =Rawdata!L29 -> 756 | I22: =Rawdata!M29 -> 935 | J22: =Rawdata!O29 -> 18054 | K22: =Rawdata!P29 -> 19095 | L22: =Rawdata!U29 -> 0.067 | M22: =Rawdata!V29 -> 0.058 | N22: =Rawdata!R29 -> 0.042 | O22: =Rawdata!S29 -> 0.034
A23: =Rawdata!C30 -> NLG | B23: =Rawdata!D30 -> BUY | C23: =Rawdata!E30 -> 44400 | D23: =Rawdata!F30 -> 7061 | E23: =Rawdata!G30 -> 8518 | F23: =Rawdata!I30 -> 634 | G23: =Rawdata!J30 -> 1200 | H23: =Rawdata!L30 -> 1580 | I23: =Rawdata!M30 -> 2991 | J23: =Rawdata!O30 -> 26730 | K23: =Rawdata!P30 -> 29846 | L23: =Rawdata!U30 -> 0.069 | M23: =Rawdata!V30 -> 0.101 | N23: =Rawdata!R30 -> 0.037 | O23: =Rawdata!S30 -> 0.049
A24: =Rawdata!C31 -> PDR | B24: =Rawdata!D31 -> BUY | C24: =Rawdata!E31 -> 23600 | D24: =Rawdata!F31 -> 4474 | E24: =Rawdata!G31 -> 6101 | F24: =Rawdata!I31 -> 641 | G24: =Rawdata!J31 -> 1410 | H24: =Rawdata!L31 -> 716 | I24: =Rawdata!M31 -> 1574 | J24: =Rawdata!O31 -> 13751 | K24: =Rawdata!P31 -> 15366 | L24: =Rawdata!U31 -> 0.068 | M24: =Rawdata!V31 -> 0.136 | N24: =Rawdata!R31 -> 0.033 | O24: =Rawdata!S31 -> 0.066
A25: =Rawdata!C32 -> VHM | B25: =Rawdata!D32 -> BUY | C25: =Rawdata!E32 -> 92500 | D25: =Rawdata!F32 -> 125810 | E25: =Rawdata!G32 -> 115136 | F25: =Rawdata!I32 -> 36602 | G25: =Rawdata!J32 -> 39843 | H25: =Rawdata!L32 -> 8893 | I25: =Rawdata!M32 -> 9681 | J25: =Rawdata!O32 -> 57975 | K25: =Rawdata!P32 -> 67675 | L25: =Rawdata!U32 -> 0.143 | M25: =Rawdata!V32 -> 0.137 | N25: =Rawdata!R32 -> 0.059 | O25: =Rawdata!S32 -> 0.048
A26: =Rawdata!C33 -> VRE | B26: =Rawdata!D33 -> BUY | C26: =Rawdata!E33 -> 31500 | D26: =Rawdata!F33 -> 9218.1678 | E26: =Rawdata!G33 -> 10941 | F26: =Rawdata!I33 -> 4413 | G26: =Rawdata!J33 -> 5355 | H26: =Rawdata!L33 -> 1895 | I26: =Rawdata!M33 -> 2299 | J26: =Rawdata!O33 -> 19897 | K26: =Rawdata!P33 -> 22196 | L26: =Rawdata!U33 -> 0.095 | M26: =Rawdata!V33 -> 0.104 | N26: =Rawdata!R33 -> 0.076 | O26: =Rawdata!S33 -> 0.088
A27: =Rawdata!C34 -> DPG | B27: =Rawdata!D34 -> BUY | C27: =Rawdata!E34 -> 53000 | D27: =Rawdata!F34 -> 4596 | E27: =Rawdata!G34 -> 5253 | F27: =Rawdata!I34 -> 270 | G27: =Rawdata!J34 -> 376 | H27: =Rawdata!L34 -> 4263 | I27: =Rawdata!M34 -> 5926 | J27: =Rawdata!O34 -> 34618 | K27: =Rawdata!P34 -> 39580 | L27: =Rawdata!U34 -> 0.122 | M27: =Rawdata!V34 -> 1.433 | N27: =Rawdata!R34 -> 0.047 | O27: =Rawdata!S34 -> 0.059
A28: =Rawdata!C36 -> IDC | B28: =Rawdata!D36 -> HOLD | C28: =Rawdata!E36 -> 65300 | D28: =Rawdata!F36 -> 7351.7871 | E28: =Rawdata!G36 -> 7572.3407 | F28: =Rawdata!I36 -> 1652.981 | G28: =Rawdata!J36 -> 1891.7298 | H28: =Rawdata!L36 -> 5009.0332 | I28: =Rawdata!M36 -> 5732.5144 | J28: =Rawdata!O36 -> 27766.102 | K28: =Rawdata!P36 -> 33498.616 | L28: =Rawdata!U36 -> 0.1598079 | M28: =Rawdata!V36 -> 0.15461271 | N28: =Rawdata!R36 -> 0.080242595 | O28: =Rawdata!S36 -> 0.08029506
A29: =Rawdata!C37 -> LHG | B29: =Rawdata!D37 -> NA | C29: =Rawdata!E37 -> 47300 | D29: =Rawdata!F37 -> 622 | E29: =Rawdata!G37 -> 0 | F29: =Rawdata!I37 -> 260 | G29: =Rawdata!J37 -> 0 | H29: =Rawdata!L37 -> 5194 | I29: =Rawdata!M37 -> 0 | J29: =Rawdata!O37 -> 37432 | K29: =Rawdata!P37 -> 0 | L29: =Rawdata!U37 -> 0.1388 | M29: =Rawdata!V37 -> 0 | N29: =Rawdata!R37 -> 0.0767 | O29: =Rawdata!S37 -> 0
A30: =Rawdata!C38 -> PHR | B30: =Rawdata!D38 -> HOLD | C30: =Rawdata!E38 -> 64800 | D30: =Rawdata!F38 -> 1645.8422 | E30: =Rawdata!G38 -> 1834.8719 | F30: =Rawdata!I38 -> 540.41102 | G30: =Rawdata!J38 -> 576.01554 | H30: =Rawdata!L38 -> 3988.2968 | I30: =Rawdata!M38 -> 4251.0624 | J30: =Rawdata!O38 -> 27756.872 | K30: =Rawdata!P38 -> 29007.934 | L30: =Rawdata!U38 -> 0.13753907 | M30: =Rawdata!V38 -> 0.1405374 | N30: =Rawdata!R38 -> 0.0786555 | O30: =Rawdata!S38 -> 0.086016352
A31: =Rawdata!C39 -> SZC | B31: =Rawdata!D39 -> BUY | C31: =Rawdata!E39 -> 45000 | D31: =Rawdata!F39 -> 1670.2676 | E31: =Rawdata!G39 -> 1743.6866 | F31: =Rawdata!I39 -> 661.77403 | G31: =Rawdata!J39 -> 759.69736 | H31: =Rawdata!L39 -> 3676.5228 | I31: =Rawdata!M39 -> 4220.5414 | J31: =Rawdata!O39 -> 22650.295 | K31: =Rawdata!P39 -> 26870.836 | L31: =Rawdata!U39 -> 0.16231677 | M31: =Rawdata!V39 -> 0.15706773 | N31: =Rawdata!R39 -> 0.06441227 | O31: =Rawdata!S39 -> 0.068991767
A32: =Rawdata!C40 -> SIP | B32: =Rawdata!D40 -> NA | C32: =Rawdata!E40 -> 0 | D32: =Rawdata!F40 -> 7479.2023 | E32: =Rawdata!G40 -> 7703.5783 | F32: =Rawdata!I40 -> 1324.4627 | G32: =Rawdata!J40 -> 1348.164 | H32: =Rawdata!L40 -> 14570.546 | I32: =Rawdata!M40 -> 14831.287 | J32: =Rawdata!O40 -> 49349.294 | K32: =Rawdata!P40 -> 55180.171 | L32: =Rawdata!U40 -> 0 | M32: =Rawdata!V40 -> 0 | N32: =Rawdata!R40 -> 0 | O32: =Rawdata!S40 -> 0
A33: =Rawdata!C41 -> DPR | B33: =Rawdata!D41 -> HOLD | C33: =Rawdata!E41 -> 49700 | D33: =Rawdata!F41 -> 1334.8685 | E33: =Rawdata!G41 -> 1385.4156 | F33: =Rawdata!I41 -> 290.58575 | G33: =Rawdata!J41 -> 317.98512 | H33: =Rawdata!L41 -> 3344.4511 | I33: =Rawdata!M41 -> 3659.7999 | J33: =Rawdata!O41 -> 27521.624 | K33: =Rawdata!P41 -> 28181.424 | L33: =Rawdata!U41 -> 0.093872926 | M33: =Rawdata!V41 -> 0.10085641 | N33: =Rawdata!R41 -> 0.059594156 | O33: =Rawdata!S41 -> 0.056648538
A34: =Rawdata!C43 -> KBC | B34: =Rawdata!D43 -> NA | C34: =Rawdata!E43 -> 35000 | D34: =Rawdata!F43 -> 5949.2776 | E34: =Rawdata!G43 -> 14924.701 | F34: =Rawdata!I43 -> 1352.2906 | G34: =Rawdata!J43 -> 5371.3018 | H34: =Rawdata!L43 -> 1761.7017 | I34: =Rawdata!M43 -> 6997.4837 | J34: =Rawdata!O43 -> 29131.542 | K34: =Rawdata!P43 -> 36867.485 | L34: =Rawdata!U43 -> 0.060474029 | M34: =Rawdata!V43 -> 0.18980095 | N34: =Rawdata!R43 -> 0.034925544 | O34: =Rawdata!S43 -> 0.11364844
A35: =Rawdata!C46 -> PLC | B35: =Rawdata!D46 -> HOLD | C35: =Rawdata!E46 -> 0 | D35: =Rawdata!F46 -> 7261.0115 | E35: =Rawdata!G46 -> 7392.4131 | F35: =Rawdata!I46 -> 118.5371 | G35: =Rawdata!J46 -> 125.51367 | H35: =Rawdata!L46 -> 1445.9693 | I35: =Rawdata!M46 -> 1552.5218 | J35: =Rawdata!O46 -> 14917.599 | K35: =Rawdata!P46 -> 14470.121 | L35: =Rawdata!U46 -> 0.096930432 | M35: =Rawdata!V46 -> 0.10729156 | N35: =Rawdata!R46 -> 0.023314333 | O35: =Rawdata!S46 -> 0.032362262
A36: =Rawdata!C47 -> DGC | B36: =Rawdata!D47 -> HOLD | C36: =Rawdata!E47 -> 109300 | D36: =Rawdata!F47 -> 10871.374 | E36: =Rawdata!G47 -> 12202.871 | F36: =Rawdata!I47 -> 3488.3822 | G36: =Rawdata!J47 -> 3865.038 | H36: =Rawdata!L47 -> 9185.2882 | I36: =Rawdata!M47 -> 10177.064 | J36: =Rawdata!O47 -> 42822.955 | K36: =Rawdata!P47 -> 50645.073 | L36: =Rawdata!U47 -> 0.24761975 | M36: =Rawdata!V47 -> 0.23153104 | N36: =Rawdata!R47 -> 0.21775575 | O36: =Rawdata!S47 -> 0.20664111
A37: =Rawdata!C48 -> CSV | B37: =Rawdata!D48 -> HOLD | C37: =Rawdata!E48 -> 0 | D37: =Rawdata!F48 -> 1987 | E37: =Rawdata!G48 -> 2086.35 | F37: =Rawdata!I48 -> 247 | G37: =Rawdata!J48 -> 266.76 | H37: =Rawdata!L48 -> 2235.2959 | I37: =Rawdata!M48 -> 2414.1196 | J37: =Rawdata!O48 -> 14063.51 | K37: =Rawdata!P48 -> 14204.145 | L37: =Rawdata!U48 -> 0.15894296 | M37: =Rawdata!V48 -> 0.16995881 | N37: =Rawdata!R48 -> 0.13286713 | O37: =Rawdata!S48 -> 0.1434965
A38: =Rawdata!C49 -> DCM | B38: =Rawdata!D49 -> BUY | C38: =Rawdata!E49 -> 47300 | D38: =Rawdata!F49 -> 19929.562 | E38: =Rawdata!G49 -> 19723.883 | F38: =Rawdata!I49 -> 2845.4463 | G38: =Rawdata!J49 -> 2621.1106 | H38: =Rawdata!L49 -> 4031.1385 | I38: =Rawdata!M49 -> 3713.3226 | J38: =Rawdata!O49 -> 22175.856 | K38: =Rawdata!P49 -> 25128.718 | L38: =Rawdata!U49 -> 0.24229828 | M38: =Rawdata!V49 -> 0.19697508 | N38: =Rawdata!R49 -> 0.16807406 | O38: =Rawdata!S49 -> 0.13888075
A39: =Rawdata!C50 -> DPM | B39: =Rawdata!D50 -> HOLD | C39: =Rawdata!E50 -> 30500 | D39: =Rawdata!F50 -> 17284.032 | E39: =Rawdata!G50 -> 17273.084 | F39: =Rawdata!I50 -> 1381.333 | G39: =Rawdata!J50 -> 1120.5364 | H39: =Rawdata!L50 -> 1905.1342 | I39: =Rawdata!M50 -> 1705.5138 | J39: =Rawdata!O50 -> 22340.519 | K39: =Rawdata!P50 -> 21949.592 | L39: =Rawdata!U50 -> 0.090927708 | M39: =Rawdata!V50 -> 0.07507419 | N39: =Rawdata!R50 -> 0.069828445 | O39: =Rawdata!S50 -> 0.048515527
A40: =Rawdata!C51 -> DDV | B40: =Rawdata!D51 -> BUY | C40: =Rawdata!E51 -> 38200 | D40: =Rawdata!F51 -> 5696.7889 | E40: =Rawdata!G51 -> 5141.5633 | F40: =Rawdata!I51 -> 485.61948 | G40: =Rawdata!J51 -> 476.58296 | H40: =Rawdata!L51 -> 3323.659 | I40: =Rawdata!M51 -> 3261.8116 | J40: =Rawdata!O51 -> 12232.17 | K40: =Rawdata!P51 -> 15065.588 | L40: =Rawdata!U51 -> 0.21240671 | M40: =Rawdata!V51 -> 0.19266528 | N40: =Rawdata!R51 -> 0.27171459 | O40: =Rawdata!S51 -> 0.21650742
A41: =Rawdata!C52 -> DRC | B41: =Rawdata!D52 -> HOLD | C41: =Rawdata!E52 -> 0 | D41: =Rawdata!F52 -> 4803.5805 | E41: =Rawdata!G52 -> 5052.3286 | F41: =Rawdata!I52 -> 108.71932 | G41: =Rawdata!J52 -> 191.47113 | H41: =Rawdata!L52 -> 648.81072 | I41: =Rawdata!M52 -> 1142.6536 | J41: =Rawdata!O52 -> 15519.442 | K41: =Rawdata!P52 -> 16266.178 | L41: =Rawdata!U52 -> 0.044973208 | M41: =Rawdata!V52 -> 0.075598331 | N41: =Rawdata!R52 -> 0.025495719 | O41: =Rawdata!S52 -> 0.043462167
A42: =Rawdata!C53 -> CSM | B42: =Rawdata!D53 -> HOLD | C42: =Rawdata!E53 -> 13500 | D42: =Rawdata!F53 -> 4799.7848 | E42: =Rawdata!G53 -> 4903.4517 | F42: =Rawdata!I53 -> 73.001339 | G42: =Rawdata!J53 -> 93.42625 | H42: =Rawdata!L53 -> 520.63913 | I42: =Rawdata!M53 -> 666.3078 | J42: =Rawdata!O53 -> 13922.444 | K42: =Rawdata!P53 -> 14568.864 | L42: =Rawdata!U53 -> 0.050599317 | M42: =Rawdata!V53 -> 0.061883167 | N42: =Rawdata!R53 -> 0.037447404 | O42: =Rawdata!S53 -> 0.043256938
A43: =Rawdata!C54 -> BSR | B43: =Rawdata!D54 -> HOLD | C43: =Rawdata!E54 -> 20100 | D43: =Rawdata!F54 -> 109209 | E43: =Rawdata!G54 -> 140582 | F43: =Rawdata!I54 -> 1196 | G43: =Rawdata!J54 -> 1293 | H43: =Rawdata!L54 -> 386 | I43: =Rawdata!M54 -> 417 | J43: =Rawdata!O54 -> 19100 | K43: =Rawdata!P54 -> 20300 | L43: =Rawdata!U54 -> 0.08 | M43: =Rawdata!V54 -> 0.08 | N43: =Rawdata!R54 -> 0.05 | O43: =Rawdata!S54 -> 0.05
A44: =Rawdata!C55 -> PVD | B44: =Rawdata!D55 -> BUY | C44: =Rawdata!E55 -> 23700 | D44: =Rawdata!F55 -> 8963 | E44: =Rawdata!G55 -> 9983 | F44: =Rawdata!I55 -> 710 | G44: =Rawdata!J55 -> 883 | H44: =Rawdata!L55 -> 1265 | I44: =Rawdata!M55 -> 1484 | J44: =Rawdata!O55 -> 28700 | K44: =Rawdata!P55 -> 29200 | L44: =Rawdata!U55 -> 0.06 | M44: =Rawdata!V55 -> 0.06 | N44: =Rawdata!R55 -> 0.041 | O44: =Rawdata!S55 -> 0.04
A45: =Rawdata!C59 -> GEX | B45: =Rawdata!D59 -> HOLD | C45: =Rawdata!E59 -> 35100 | D45: =Rawdata!F59 -> 38136.903 | E45: =Rawdata!G59 -> 38892.552 | F45: =Rawdata!I59 -> 1129.6703 | G45: =Rawdata!J59 -> 1292.1494 | H45: =Rawdata!L59 -> 1314.4872 | I45: =Rawdata!M59 -> 1503.5483 | J45: =Rawdata!O59 -> 29923.46 | K45: =Rawdata!P59 -> 32823.469 | L45: =Rawdata!U59 -> 0.089012451 | M45: =Rawdata!V59 -> 0.095088397 | N45: =Rawdata!R59 -> 0.045397963 | O45: =Rawdata!S59 -> 0.044737672
A46: =Rawdata!C60 -> BWE | B46: =Rawdata!D60 -> HOLD | C46: =Rawdata!E60 -> 42100 | D46: =Rawdata!F60 -> 4262.7199 | E46: =Rawdata!G60 -> 4555.3088 | F46: =Rawdata!I60 -> 695.96081 | G46: =Rawdata!J60 -> 884 | H46: =Rawdata!L60 -> 3164.8968 | I46: =Rawdata!M60 -> 4097.2114 | J46: =Rawdata!O60 -> 27805.355 | K46: =Rawdata!P60 -> 31300.401 | L46: =Rawdata!U60 -> 0.1239787 | M46: =Rawdata!V60 -> 0.14248695 | N46: =Rawdata!R60 -> 0.050910362 | O46: =Rawdata!S60 -> 0.065080959
A47: =Rawdata!C61 -> DHC | B47: =Rawdata!D61 -> BUY | C47: =Rawdata!E61 -> 35100 | D47: =Rawdata!F61 -> 3624.3448 | E47: =Rawdata!G61 -> 3714.0387 | F47: =Rawdata!I61 -> 308.74048 | G47: =Rawdata!J61 -> 322.13148 | H47: =Rawdata!L61 -> 3196.0712 | I47: =Rawdata!M61 -> 3334.6944 | J47: =Rawdata!O61 -> 22388.618 | K47: =Rawdata!P61 -> 25723.312 | L47: =Rawdata!U61 -> 0.14822838 | M47: =Rawdata!V61 -> 0.15917111 | N47: =Rawdata!R61 -> 0.088286099 | O47: =Rawdata!S61 -> 0.083152035
A48: =Rawdata!C62 -> HDG | B48: =Rawdata!D62 -> BUY | C48: =Rawdata!E62 -> 33100 | D48: =Rawdata!F62 -> 3200.3596 | E48: =Rawdata!G62 -> 3675.3972 | F48: =Rawdata!I62 -> 882.56169 | G48: =Rawdata!J62 -> 1337.736 | H48: =Rawdata!L62 -> 2624.3286 | I48: =Rawdata!M62 -> 3977.8055 | J48: =Rawdata!O62 -> 25150.473 | K48: =Rawdata!P62 -> 29813.373 | L48: =Rawdata!U62 -> 0.13494248 | M48: =Rawdata!V62 -> 0.17485763 | N48: =Rawdata!R62 -> 0.076298339 | O48: =Rawdata!S62 -> 0.097990445
A49: =Rawdata!C63 -> NT2 | B49: =Rawdata!D63 -> HOLD | C49: =Rawdata!E63 -> 25300 | D49: =Rawdata!F63 -> 7381.2259 | E49: =Rawdata!G63 -> 7559.6851 | F49: =Rawdata!I63 -> 528.85739 | G49: =Rawdata!J63 -> 724.74411 | H49: =Rawdata!L63 -> 1837.1012 | I49: =Rawdata!M63 -> 2517.5563 | J49: =Rawdata!O63 -> 17388.761 | K49: =Rawdata!P63 -> 21406.286 | L49: =Rawdata!U63 -> 0.11503292 | M49: =Rawdata!V63 -> 0.12978751 | N49: =Rawdata!R63 -> 0.055877451 | O49: =Rawdata!S63 -> 0.067156397
A50: =Rawdata!C64 -> QTP | B50: =Rawdata!D64 -> BUY | C50: =Rawdata!E64 -> 12900 | D50: =Rawdata!F64 -> 12106.81 | E50: =Rawdata!G64 -> 12129.313 | F50: =Rawdata!I64 -> 783.61944 | G50: =Rawdata!J64 -> 724.08522 | H50: =Rawdata!L64 -> 1741.3765 | I50: =Rawdata!M64 -> 1609.0783 | J50: =Rawdata!O64 -> 11500 | K50: =Rawdata!P64 -> 11700 | L50: =Rawdata!U64 -> 0.15244596 | M50: =Rawdata!V64 -> 0.13873591 | N50: =Rawdata!R64 -> 0.10686118 | O50: =Rawdata!S64 -> 0.098462112
A51: =Rawdata!C65 -> PC1 | B51: =Rawdata!D65 -> BUY | C51: =Rawdata!E65 -> 26700 | D51: =Rawdata!F65 -> 12788.225 | E51: =Rawdata!G65 -> 14525.777 | F51: =Rawdata!I65 -> 559.2402 | G51: =Rawdata!J65 -> 1157.3368 | H51: =Rawdata!L65 -> 1563.8708 | I51: =Rawdata!M65 -> 3236.4004 | J51: =Rawdata!O65 -> 23760.341 | K51: =Rawdata!P65 -> 27864.524 | L51: =Rawdata!U65 -> 0.096304461 | M51: =Rawdata!V65 -> 0.15900027 | N51: =Rawdata!R65 -> 0.03595861 | O51: =Rawdata!S65 -> 0.066343784
A52: =Rawdata!C66 -> POW | B52: =Rawdata!D66 -> BUY | C52: =Rawdata!E66 -> 17700 | D52: =Rawdata!F66 -> 41988.326 | E52: =Rawdata!G66 -> 60550.125 | F52: =Rawdata!I66 -> 1562.5086 | G52: =Rawdata!J66 -> 2122.3378 | H52: =Rawdata!L66 -> 667.22548 | I52: =Rawdata!M66 -> 906.28481 | J52: =Rawdata!O66 -> 15512.888 | K52: =Rawdata!P66 -> 16573.314 | L52: =Rawdata!U66 -> 0.052331989 | M52: =Rawdata!V66 -> 0.066098564 | N52: =Rawdata!R66 -> 0.021695892 | O52: =Rawdata!S66 -> 0.027015317
A53: =Rawdata!C67 -> REE | B53: =Rawdata!D67 -> HOLD | C53: =Rawdata!E67 -> 67300 | D53: =Rawdata!F67 -> 10132.351 | E53: =Rawdata!G67 -> 12098.999 | F53: =Rawdata!I67 -> 2486.9169 | G53: =Rawdata!J67 -> 3043 | H53: =Rawdata!L67 -> 5279.4188 | I53: =Rawdata!M67 -> 6556.7218 | J53: =Rawdata!O67 -> 54200.079 | K53: =Rawdata!P67 -> 62262.309 | L53: =Rawdata!U67 -> 0.12821127 | M53: =Rawdata!V67 -> 0.13845208 | N53: =Rawdata!R67 -> 0.08300492 | O53: =Rawdata!S67 -> 0.096570825
A54: =Rawdata!C68 -> VEA | B54: =Rawdata!D68 -> HOLD | C54: =Rawdata!E68 -> 41500 | D54: =Rawdata!F68 -> 4321.0147 | E54: =Rawdata!G68 -> 4387.8945 | F54: =Rawdata!I68 -> 7293.4831 | G54: =Rawdata!J68 -> 7444.501 | H54: =Rawdata!L68 -> 5488.7742 | I54: =Rawdata!M68 -> 5602.424 | J54: =Rawdata!O68 -> 19802.284 | K54: =Rawdata!P68 -> 19860.106 | L54: =Rawdata!U68 -> 0.28044071 | M54: =Rawdata!V68 -> 0.28542133 | N54: =Rawdata!R68 -> 0.26691027 | O54: =Rawdata!S68 -> 0.27156914
A55: =Rawdata!C69 -> VGC | B55: =Rawdata!D69 -> HOLD | C55: =Rawdata!E69 -> 46100 | D55: =Rawdata!F69 -> 12419.734 | E55: =Rawdata!G69 -> 12210.714 | F55: =Rawdata!I69 -> 1109.826 | G55: =Rawdata!J69 -> 1068.29 | H55: =Rawdata!L69 -> 2475.0803 | I55: =Rawdata!M69 -> 2382.4488 | J55: =Rawdata!O69 -> 24110.108 | K55: =Rawdata!P69 -> 26754.251 | L55: =Rawdata!U69 -> 0.12437947 | M55: =Rawdata!V69 -> 0.10396839 | N55: =Rawdata!R69 -> 0.050983535 | O55: =Rawdata!S69 -> 0.044888866
A56: =Rawdata!C70 -> PVS | B56: =Rawdata!D70 -> BUY | C56: =Rawdata!E70 -> 38600 | D56: =Rawdata!F70 -> 36151 | E56: =Rawdata!G70 -> 43138 | F56: =Rawdata!I70 -> 1177 | G56: =Rawdata!J70 -> 1061 | H56: =Rawdata!L70 -> 1847 | I56: =Rawdata!M70 -> 1665 | J56: =Rawdata!O70 -> 27850 | K56: =Rawdata!P70 -> 30060 | L56: =Rawdata!U70 -> 0.09 | M56: =Rawdata!V70 -> 0.08 | N56: =Rawdata!R70 -> 0.047 | O56: =Rawdata!S70 -> 0.04
... A90: =Rawdata!C104 -> TCH | B90: =Rawdata!D104 -> NA | C90: =Rawdata!E104 -> 22400 | D90: =Rawdata!F104 -> 3963 | E90: =Rawdata!G104 -> 6617 | F90: =Rawdata!I104 -> 997 | G90: =Rawdata!J104 -> 2358 | H90: =Rawdata!L104 -> 1492 | I90: =Rawdata!M104 -> 3528 | J90: =Rawdata!O104 -> 15564 | K90: =Rawdata!P104 -> 18392 | L90: =Rawdata!U104 -> 0.082 | M90: =Rawdata!V104 -> 0.145 | N90: =Rawdata!R104 -> 0.066 | O90: =Rawdata!S104 -> 0.12

Sheet Rawdata
B1: ENTRY HUB FROM ANALYSTS | I1: A/c mình không filter bảng này để tránh Copy/Paste nhầm dữ liệu bạn khác | P1: Chọn ngôn ngữ | Q1: Tiếng Việt
B2: 2025
B3: Update time: | C3: {=[1]!latest_updatedate[Update time]} -> 45881
F5: Revenue | I5: NPATMI | L5: EPS | O5: BVPS | R5: ROA | U5: ROE | X5: =V5 -> 0 | Y5: EBITDA | AB5: NET DEBT | AE5: =X5 -> 0 | AF5: =AE5 -> 0
B6: Analyst | C6: Ticker | D6: Rating | E6: Target Price | F6: =$B$2 -> 2025 | G6: =F6+1 -> 2026 | H6: =G6+1 -> 2027 | I6: =$B$2 -> 2025 | J6: =I6+1 -> 2026 | K6: =J6+1 -> 2027 | L6: =$B$2 -> 2025 | M6: =L6+1 -> 2026 | N6: =M6+1 -> 2027 | O6: =$B$2 -> 2025 | P6: =O6+1 -> 2026 | Q6: =P6+1 -> 2027 | R6: =$B$2 -> 2025 | S6: =R6+1 -> 2026 | T6: =S6+1 -> 2027 | U6: =$B$2 -> 2025 | V6: =U6+1 -> 2026 | W6: =V6+1 -> 2027 | X6: Forecast Y/N | Y6: =$B$2 -> 2025 | Z6: =Y6+1 -> 2026 | AA6: =Z6+1 -> 2027 | AB6: =$B$2 -> 2025 | AC6: =AB6+1 -> 2026 | AD6: =AC6+1 -> 2027 | AE6: Giá hiện tại | AF6: % | AI6: 2023 | AJ6: 2023 | AK6: 2023 | AL6: 2023 | AM6: 2023 | AN6: 2023
B7: Analyst | C7: Ticker | D7: Rating | E7: Target Price | F7: REV_FY | G7: REV_FY+1 | H7: REV_FY+2 | I7: NPATMI_FY | J7: NPATMI_FY+1 | K7: NPATMI_FY+2 | L7: EPS_FY | M7: EPS_FY+1 | N7: EPS_FY+2 | O7: BVPS_FY | P7: BVPS_FY+1 | Q7: BVPS_FY+2 | R7: ROA_FY | S7: ROA_FY+1 | T7: ROA_FY+2 | U7: ROE_FY | V7: ROE_FY+1 | W7: ROE_FY+2 | X7: Forecast Y/N | Y7: EBITDA_FY | Z7: EBITDA_FY+1 | AA7: EBITDA_FY+2 | AB7: NDEBT_FY | AC7: NDEBT_FY+1 | AD7: NDEBT_FY+2 | AE7: PRCIE_CURRENT | AF7: Upside | AI7: REV_FY | AJ7: NPATMI_FY | AK7: EPS_FY | AL7: BVPS_FY | AM7: ROA_FY | AN7: ROE_FY
B8: Đoàn Minh Trí | C8: BID | D8: BUY | E8: 45000 | F8: 86855.1 | G8: 100748.43 | I8: 26773.327 | J8: 31143.59 | L8: 3760.9871 | M8: 4202.5156 | O8: 26098.276 | P8: 29272.438 | R8: 0.0089920402 | S8: 0.0090446045 | U8: 0.16452466 | V8: 0.15466813 | X8: =IF(OR(COUNTBLANK(A_Entry_Forecast[[#This Row],[REV_FY]])<>0,COUNTBLANK(A_Entry_Forecast[[#This Row],[REV_FY+1]])<>0),"N","Y") -> Y | AE8: =VLOOKUP(A_Entry_Forecast[[#This Row],[Ticker]],[1]!A_Entry_Data[#Data],2,FALSE) -> 41500 | AF8: =IF(A_Entry_Forecast[[#This Row],[Target Price]]<>0,A_Entry_Forecast[[#This Row],[Target Price]]/AE8-1,"") -> 0.084337349 | AH8: ACB | AI8: 0 | AJ8: 16044.733 | AK8: 4092 | AL8: 18268.55 | AM8: 0.0242 | AN8: 0.248
B9: Đoàn Minh Trí | C9: CTG | D9: BUY | E9: 52500 | F9: 92204.892 | G9: 105994.33 | I9: 29994.821 | J9: 36534.267 | L9: 5585.6364 | M9: 5803.9342 | O9: 33059.418 | P9: 34006.648 | R9: 0.011769472 | S9: 0.012658663 | U9: 0.18454787 | V9: 0.18659359 | X9: =IF(OR(COUNTBLANK(A_Entry_Forecast[[#This Row],[REV_FY]])<>0,COUNTBLANK(A_Entry_Forecast[[#This Row],[REV_FY+1]])<>0),"N","Y") -> Y | AE9: =VLOOKUP(A_Entry_Forecast[[#This Row],[Ticker]],[1]!A_Entry_Data[#Data],2,FALSE) -> 48000 | AF9: =IF(A_Entry_Forecast[[#This Row],[Target Price]]<>0,A_Entry_Forecast[[#This Row],[Target Price]]/AE9-1,"") -> 0.09375 | AH9: BID | AI9: 0 | AJ9: 21551.779 | AK9: 0 | AL9: 20691.5 | AM9: 0.0097 | AN9: 0.1983
B10: Đoàn Minh Trí | C10: VCB | D10: BUY | E10: 76000 | F10: 74171.354 | G10: 85650.802 | I10: 35307.008 | J10: 41707.746 | L10: 4225.5041 | M10: 4991.5373 | O10: 27696.082 | P10: 36959.264 | R10: 0.015613357 | S10: 0.015649895 | U10: 0.1651663 | V10: 0.15440447 | X10: =IF(OR(COUNTBLANK(A_Entry_Forecast[[#This Row],[REV_FY]])<>0,COUNTBLANK(A_Entry_Forecast[[#This Row],[REV_FY+1]])<>0),"N","Y") -> Y | AE10: =VLOOKUP(A_Entry_Forecast[[#This Row],[Ticker]],[1]!A_Entry_Data[#Data],2,FALSE) -> 63000 | AF10: =IF(A_Entry_Forecast[[#This Row],[Target Price]]<>0,A_Entry_Forecast[[#This Row],[Target Price]]/AE10-1,"") -> 0.20634921 | AH10: MBB | AI10: 0 | AJ10: 20676.788 | AK10: 0 | AL10: 17786.07 | AM10: 0.0247 | AN10: 0.2451
B11: Đoàn Minh Trí | C11: HDB | D11: BUY | E11: 31000 | F11: 40259.7 | G11: 49782.05 | I11: 15580.847 | J11: 19865.033 | L11: 3712.2984 | M11: 3941.8475 | O11: 16695.368 | P11: 17846.327 | R11: 0.019724712 | S11: 0.019989579 | U11: 0.25016804 | V11: 0.24829904 | X11: =IF(OR(COUNTBLANK(A_Entry_Forecast[[#This Row],[REV_FY]])<>0,COUNTBLANK(A_Entry_Forecast[[#This Row],[REV_FY+1]])<>0),"N","Y") -> Y | AE11: =VLOOKUP(A_Entry_Forecast[[#This Row],[Ticker]],[1]!A_Entry_Data[#Data],2,FALSE) -> 28900 | AF11: =IF(A_Entry_Forecast[[#This Row],[Target Price]]<>0,A_Entry_Forecast[[#This Row],[Target Price]]/AE11-1,"") -> 0.07266436 | AH11: CTG | AI11: 0 | AJ11: 19992.233 | AK11: 0 | AL11: 23595.8 | AM11: 0.0104 | AN11: 0.1708
B12: Đoàn Minh Trí | C12: MBB | D12: BUY | E12: 33000 | F12: 65788.201 | G12: 82056.214 | I12: 25355.979 | J12: 30675.762 | L12: 3613.177 | M12: 4371.2356 | O12: 19159.363 | P12: 23530.599 | R12: 0.019689728 | S12: 0.018550651 | U12: 0.20564273 | V12: 0.20478986 | X12: =IF(OR(COUNTBLANK(A_Entry_Forecast[[#This Row],[REV_FY]])<>0,COUNTBLANK(A_Entry_Forecast[[#This Row],[REV_FY+1]])<>0),"N","Y") -> Y | AE12: =VLOOKUP(A_Entry_Forecast[[#This Row],[Ticker]],[1]!A_Entry_Data[#Data],2,FALSE) -> 32400 | AF12: =IF(A_Entry_Forecast[[#This Row],[Target Price]]<>0,A_Entry_Forecast[[#This Row],[Target Price]]/AE12-1,"") -> 0.018518519 | AH12: HDB | AI12: 0 | AJ12: 10070.898 | AK12: 3482 | AL12: 15293.84 | AM12: 0.0198 | AN12: 0.2474
B13: Đoàn Minh Trí | C13: TCB | D13: BUY | E13: 42000 | F13: 54304.021 | G13: 65366.62 | I13: 24829.701 | J13: 30000.567 | L13: 3511.8801 | M13: 4233.6299 | O13: 23110.798 | P13: 26591.298 | R13: 0.023218685 | S13: 0.023451142 | U13: 0.16080519 | V13: 0.17053982 | X13: =IF(OR(COUNTBLANK(A_Entry_Forecast[[#This Row],[REV_FY]])<>0,COUNTBLANK(A_Entry_Forecast[[#This Row],[REV_FY+1]])<>0),"N","Y") -> Y | AE13: =VLOOKUP(A_Entry_Forecast[[#This Row],[Ticker]],[1]!A_Entry_Data[#Data],2,FALSE) -> 37700 | AF13: =IF(A_Entry_Forecast[[#This Row],[Target Price]]<>0,A_Entry_Forecast[[#This Row],[Target Price]]/AE13-1,"") -> 0.11405836 | AH13: LPB | AI13: 0 | AJ13: 5572.246 | AK13: -2703 | AL13: 13339.53 | AM13: 0.0157 | AN13: 0.1916
B14: Đoàn Minh Trí | C14: VPB | D14: BUY | E14: 27000 | F14: 70386.133 | G14: 83310.406 | I14: 18274.466 | J14: 21970.001 | L14: 2303.3396 | M14: 2769.13 | O14: 19689.244 | P14: 21458.374 | R14: 0.018052079 | S14: 0.017838786 | U14: 0.1225991 | V14: 0.13459491 | X14: =IF(OR(COUNTBLANK(A_Entry_Forecast[[#This Row],[REV_FY]])<>0,COUNTBLANK(A_Entry_Forecast[[#This Row],[REV_FY+1]])<>0),"N","Y") -> Y | AE14: =VLOOKUP(A_Entry_Forecast[[#This Row],[Ticker]],[1]!A_Entry_Data[#Data],2,FALSE) -> 29600 | AF14: =IF(A_Entry_Forecast[[#This Row],[Target Price]]<>0,A_Entry_Forecast[[#This Row],[Target Price]]/AE14-1,"") -> -0.087837838 | AH14: STB | AI14: 0 | AJ14: 7718.616 | AK14: 4094 | AL14: 24259.22 | AM14: 0.0122 | AN14: 0.183
B15: Dương Quang Minh | C15: ACB | D15: BUY | E15: 26400 | F15: 37297.512 | G15: 42675.061 | I15: 18939.743 | J15: 21965.66 | L15: 4240.2492 | M15: 4917.6947 | O15: 21692.616 | P15: 25084.816 | R15: 0.020531521 | S15: 0.020800811 | U15: 0.21002716 | V15: 0.21025929 | X15: =IF(OR(COUNTBLANK(A_Entry_Forecast[[#This Row],[REV_FY]])<>0,COUNTBLANK(A_Entry_Forecast[[#This Row],[REV_FY+1]])<>0),"N","Y") -> Y | AE15: =VLOOKUP(A_Entry_Forecast[[#This Row],[Ticker]],[1]!A_Entry_Data[#Data],2,FALSE) -> 24250 | AF15: =IF(A_Entry_Forecast[[#This Row],[Target Price]]<>0,A_Entry_Forecast[[#This Row],[Target Price]]/AE15-1,"") -> 0.088659794 | AH15: TCB | AI15: 0 | AJ15: 18003.802 | AK15: 0 | AL15: 36993.85 | AM15: 0.0233 | AN15: 0.1484
B16: Dương Quang Minh | C16: MSB | D16: HOLD | E16: 14000 | F16: 15880.374 | G16: 18011.717 | I16: 6436.1291 | J16: 7496.3334 | L16: 2475.4343 | M16: 2883.2052 | O16: 15965 | P16: 18390.925 | R16: 0.018940011 | S16: 0.01926098 | U16: 0.16434091 | V16: 0.16784326 | X16: =IF(OR(COUNTBLANK(A_Entry_Forecast[[#This Row],[REV_FY]])<>0,COUNTBLANK(A_Entry_Forecast[[#This Row],[REV_FY+1]])<>0),"N","Y") -> Y | AE16: =VLOOKUP(A_Entry_Forecast[[#This Row],[Ticker]],[1]!A_Entry_Data[#Data],2,FALSE) -> 15400 | AF16: =IF(A_Entry_Forecast[[#This Row],[Target Price]]<>0,A_Entry_Forecast[[#This Row],[Target Price]]/AE16-1,"") -> -0.090909091 | AH16: TPB | AI16: 0 | AJ16: 4463.12 | AK16: 0 | AL16: 14872 | AM16: 0.013 | AN16: 0.1374
B17: Dương Quang Minh | C17: STB | D17: HOLD | E17: 49000 | F17: 32623.844 | G17: 37000.294 | I17: 11837.217 | J17: 13648.491 | L17: 6278.972 | M17: 7239.7505 | O17: 33615.288 | P17: 37752.746 | R17: 0.014979945 | S17: 0.014481271 | U17: 0.20004736 | V17: 0.20288496 | X17: =IF(OR(COUNTBLANK(A_Entry_Forecast[[#This Row],[REV_FY]])<>0,COUNTBLANK(A_Entry_Forecast[[#This Row],[REV_FY+1]])<>0),"N","Y") -> Y | AE17: =VLOOKUP(A_Entry_Forecast[[#This Row],[Ticker]],[1]!A_Entry_Data[#Data],2,FALSE) -> 54000 | AF17: =IF(A_Entry_Forecast[[#This Row],[Target Price]]<>0,A_Entry_Forecast[[#This Row],[Target Price]]/AE17-1,"") -> -0.092592593 | AH17: VCB | AI17: 0 | AJ17: 33033.203 | AK17: -5910 | AL17: 30138.95 | AM17: 0.0181 | AN17: 0.2173
B18: Dương Quang Minh | C18: TPB | D18: HOLD | E18: 15500 | F18: 19423.168 | G18: 21759.822 | I18: 6816.0784 | J18: 7932.9675 | L18: 2579.9362 | M18: 3002.687 | O18: 15483.398 | P18: 17011.735 | R18: 0.01568287 | S18: 0.015686145 | U18: 0.17365192 | V18: 0.18480841 | X18: =IF(OR(COUNTBLANK(A_Entry_Forecast[[#This Row],[REV_FY]])<>0,COUNTBLANK(A_Entry_Forecast[[#This Row],[REV_FY+1]])<>0),"N","Y") -> Y | AE18: =VLOOKUP(A_Entry_Forecast[[#This Row],[Ticker]],[1]!A_Entry_Data[#Data],2,FALSE) -> 19200 | AF18: =IF(A_Entry_Forecast[[#This Row],[Target Price]]<>0,A_Entry_Forecast[[#This Row],[Target Price]]/AE18-1,"") -> -0.19270833 | AH18: VIB | AI18: 0 | AJ18: 8562.421 | AK18: 3332 | AL18: 14955.39 | AM18: 0.0228 | AN18: 0.2426
B19: Dương Quang Minh | C19: VIB | D19: BUY | E19: 22200 | F19: 22804.392 | G19: 26838.704 | I19: 8744.8515 | J19: 10812.779 | L19: 2935.3731 | M19: 3629.5117 | O19: 16421.647 | P19: 19298.312 | R19: 0.016421619 | S19: 0.017479293 | U19: 0.19265184 | V19: 0.20322037 | X19: =IF(OR(COUNTBLANK(A_Entry_Forecast[[#This Row],[REV_FY]])<>0,COUNTBLANK(A_Entry_Forecast[[#This Row],[REV_FY+1]])<>0),"N","Y") -> Y | AE19: =VLOOKUP(A_Entry_Forecast[[#This Row],[Ticker]],[1]!A_Entry_Data[#Data],2,FALSE) -> 19900 | AF19: =IF(A_Entry_Forecast[[#This Row],[Target Price]]<>0,A_Entry_Forecast[[#This Row],[Target Price]]/AE19-1,"") -> 0.11557789 | AH19: VPB | AI19: 0 | AJ19: 10052.574 | AK19: 1445 | AL19: 16979.51 | AM19: 0.0139 | AN19: 0.0868
... B27: Lâm Việt | C27: DXG | D27: BUY | E27: 21900 | F27: 3146.8479 | G27: 18030.777 | I27: 223.5037 | J27: 2673.3262 | L27: 309.36869 | M27: 3700.3569 | O27: 15504.364 | P27: 19204.721 | R27: 0.011452492 | S27: 0.079828726 | U27: 0.022910025 | V27: 0.21508707 | X27: =IF(OR(COUNTBLANK(A_Entry_Forecast[[#This Row],[REV_FY]])<>0,COUNTBLANK(A_Entry_Forecast[[#This Row],[REV_FY+1]])<>0),"N","Y") -> Y | AE27: =VLOOKUP(A_Entry_Forecast[[#This Row],[Ticker]],[1]!A_Entry_Data[#Data],2,FALSE) -> 21550 | AF27: =IF(A_Entry_Forecast[[#This Row],[Target Price]]<>0,A_Entry_Forecast[[#This Row],[Target Price]]/AE27-1,"") -> 0.016241299 | AH27: GEX | AI27: 29998.097 | AJ27: 331.02137 | AK27: 389 | AL27: 14507.43 | AM27: 0.0062 | AN27: 0.0708
B28: Lâm Việt | C28: IJC | D28: NA | X28: =IF(OR(COUNTBLANK(A_Entry_Forecast[[#This Row],[REV_FY]])<>0,COUNTBLANK(A_Entry_Forecast[[#This Row],[REV_FY+1]])<>0),"N","Y") -> N | AE28: =VLOOKUP(A_Entry_Forecast[[#This Row],[Ticker]],[1]!A_Entry_Data[#Data],2,FALSE) -> 14000 | AF28: =IF(A_Entry_Forecast[[#This Row],[Target Price]]<>0,A_Entry_Forecast[[#This Row],[Target Price]]/AE28-1,"") | AH28: OIL | AI28: 102668.9 | AJ28: 576.72853 | AK28: 455 | AL28: 10026.12 | AM28: 0.0171 | AN28: 0.061
B29: Lâm Việt | C29: KDH | D29: BUY | E29: 39900 | F29: 4540 | G29: 4637 | I29: 811 | J29: 1003 | L29: 756 | M29: 935 | O29: 18054 | P29: 19095 | R29: 0.042 | S29: 0.034 | U29: 0.067 | V29: 0.058 | X29: =IF(OR(COUNTBLANK(A_Entry_Forecast[[#This Row],[REV_FY]])<>0,COUNTBLANK(A_Entry_Forecast[[#This Row],[REV_FY+1]])<>0),"N","Y") -> Y | AE29: =VLOOKUP(A_Entry_Forecast[[#This Row],[Ticker]],[1]!A_Entry_Data[#Data],2,FALSE) -> 34200 | AF29: =IF(A_Entry_Forecast[[#This Row],[Target Price]]<>0,A_Entry_Forecast[[#This Row],[Target Price]]/AE29-1,"") -> 0.16666667 | AH29: PLC | AI29: 7960.6537 | AJ29: 107.73852 | AK29: 1333 | AL29: 16328.88 | AM29: 0.0243 | AN29: 0.0846
B30: Lâm Việt | C30: NLG | D30: BUY | E30: 44400 | F30: 7061 | G30: 8518 | I30: 634 | J30: 1200 | L30: 1580 | M30: 2991 | O30: 26730 | P30: 29846 | R30: 0.037 | S30: 0.049 | U30: 0.069 | V30: 0.101 | X30: =IF(OR(COUNTBLANK(A_Entry_Forecast[[#This Row],[REV_FY]])<>0,COUNTBLANK(A_Entry_Forecast[[#This Row],[REV_FY+1]])<>0),"N","Y") -> Y | AE30: =VLOOKUP(A_Entry_Forecast[[#This Row],[Ticker]],[1]!A_Entry_Data[#Data],2,FALSE) -> 43550 | AF30: =IF(A_Entry_Forecast[[#This Row],[Target Price]]<>0,A_Entry_Forecast[[#This Row],[Target Price]]/AE30-1,"") -> 0.019517796 | AH30: PLX | AI30: 274252.67 | AJ30: 2811.9796 | AK30: 2111 | AL30: 20036.58 | AM30: 0.0367 | AN30: 0.1211
B31: Lâm Việt | C31: PDR | D31: BUY | E31: 23600 | F31: 4474 | G31: 6101 | I31: 641 | J31: 1410 | L31: 716 | M31: 1574 | O31: 13751 | P31: 15366 | R31: 0.033 | S31: 0.066 | U31: 0.068 | V31: 0.136 | X31: =IF(OR(COUNTBLANK(A_Entry_Forecast[[#This Row],[REV_FY]])<>0,COUNTBLANK(A_Entry_Forecast[[#This Row],[REV_FY+1]])<>0),"N","Y") -> Y | AE31: =VLOOKUP(A_Entry_Forecast[[#This Row],[Ticker]],[1]!A_Entry_Data[#Data],2,FALSE) -> 23900 | AF31: =IF(A_Entry_Forecast[[#This Row],[Target Price]]<>0,A_Entry_Forecast[[#This Row],[Target Price]]/AE31-1,"") -> -0.012552301 | AH31: PVD | AI31: 5811.6852 | AJ31: 579.35605 | AK31: 803 | AL31: 26347.14 | AM31: 0.0274 | AN31: 0.0379
B32: Lâm Việt | C32: VHM | D32: BUY | E32: 92500 | F32: 125810 | G32: 115136 | I32: 36602 | J32: 39843 | L32: 8893 | M32: 9681 | O32: 57975 | P32: 67675 | R32: 0.059 | S32: 0.048 | U32: 0.143 | V32: 0.137 | X32: =IF(OR(COUNTBLANK(A_Entry_Forecast[[#This Row],[REV_FY]])<>0,COUNTBLANK(A_Entry_Forecast[[#This Row],[REV_FY+1]])<>0),"N","Y") -> Y | AE32: =VLOOKUP(A_Entry_Forecast[[#This Row],[Ticker]],[1]!A_Entry_Data[#Data],2,FALSE) -> 93000 | AF32: =IF(A_Entry_Forecast[[#This Row],[Target Price]]<>0,A_Entry_Forecast[[#This Row],[Target Price]]/AE32-1,"") -> -0.0053763441 | AH32: PVS | AI32: 19349.376 | AJ32: 866.11733 | AK32: 0 | AL32: 26516.39 | AM32: 0.0332 | AN32: 0.0723
B33: Lâm Việt | C33: VRE | D33: BUY | E33: 31500 | F33: 9218.1678 | G33: 10941 | I33: 4413 | J33: 5355 | L33: 1895 | M33: 2299 | O33: 19897 | P33: 22196 | R33: 0.076 | S33: 0.088 | U33: 0.095 | V33: 0.104 | X33: =IF(OR(COUNTBLANK(A_Entry_Forecast[[#This Row],[REV_FY]])<>0,COUNTBLANK(A_Entry_Forecast[[#This Row],[REV_FY+1]])<>0),"N","Y") -> Y | AE33: =VLOOKUP(A_Entry_Forecast[[#This Row],[Ticker]],[1]!A_Entry_Data[#Data],2,FALSE) -> 29450 | AF33: =IF(A_Entry_Forecast[[#This Row],[Target Price]]<>0,A_Entry_Forecast[[#This Row],[Target Price]]/AE33-1,"") -> 0.069609508
B34: Lâm Việt | C34: DPG | D34: BUY | E34: 53000 | F34: 4596 | G34: 5253 | I34: 270 | J34: 376 | L34: 4263 | M34: 5926 | O34: 34618 | P34: 39580 | R34: 0.047 | S34: 0.059 | U34: 0.122 | V34: 1.433 | X34: =IF(OR(COUNTBLANK(A_Entry_Forecast[[#This Row],[REV_FY]])<>0,COUNTBLANK(A_Entry_Forecast[[#This Row],[REV_FY+1]])<>0),"N","Y") -> Y | AE34: =VLOOKUP(A_Entry_Forecast[[#This Row],[Ticker]],[1]!A_Entry_Data[#Data],2,FALSE) -> 47800 | AF34: =IF(A_Entry_Forecast[[#This Row],[Target Price]]<>0,A_Entry_Forecast[[#This Row],[Target Price]]/AE34-1,"") -> 0.10878661 | AH34: GAS | AI34: 89953.907 | AJ34: 11606.031 | AK34: 4972 | AL34: 27886.8 | AM34: 0.1362 | AN34: 0.1904
B35: Lâm Việt | C35: GVR | D35: HOLD | G35: =A_Entry_Forecast[[#This Row],[REV_FY+1]]*1.03 -> 0 | I35: =A_Entry_Forecast[[#This Row],[NPATMI_FY]]*1.09 -> 0 | J35: =A_Entry_Forecast[[#This Row],[NPATMI_FY+1]]*1.15 -> 0 | L35: 899 | O35: 14974 | R35: 0.0404 | U35: 0.0559 | X35: =IF(OR(COUNTBLANK(A_Entry_Forecast[[#This Row],[REV_FY]])<>0,COUNTBLANK(A_Entry_Forecast[[#This Row],[REV_FY+1]])<>0),"N","Y") -> N | AE35: =VLOOKUP(A_Entry_Forecast[[#This Row],[Ticker]],[1]!A_Entry_Data[#Data],2,FALSE) -> 32450 | AF35: =IF(A_Entry_Forecast[[#This Row],[Target Price]]<>0,A_Entry_Forecast[[#This Row],[Target Price]]/AE35-1,"") | AH35: IJC | AI35: 1493.7132 | AJ35: 395.03853 | AK35: 1489 | AL35: 15184.08 | AM35: 0.0612 | AN35: 0.1034
B36: Lâm Việt | C36: IDC | D36: HOLD | E36: 65300 | F36: 7351.7871 | G36: 7572.3407 | I36: 1652.981 | J36: 1891.7298 | L36: 5009.0332 | M36: 5732.5144 | O36: 27766.102 | P36: 33498.616 | R36: 0.080242595 | S36: 0.08029506 | U36: 0.1598079 | V36: 0.15461271 | X36: =IF(OR(COUNTBLANK(A_Entry_Forecast[[#This Row],[REV_FY]])<>0,COUNTBLANK(A_Entry_Forecast[[#This Row],[REV_FY+1]])<>0),"N","Y") -> Y | AE36: =VLOOKUP(A_Entry_Forecast[[#This Row],[Ticker]],[1]!A_Entry_Data[#Data],2,FALSE) -> 49500 | AF36: =IF(A_Entry_Forecast[[#This Row],[Target Price]]<>0,A_Entry_Forecast[[#This Row],[Target Price]]/AE36-1,"") -> 0.31919192 | AH36: DXG | AI36: 3705.9586 | AJ36: 176.33303 | AK36: 289 | AL36: 15377.3 | AM36: 0.006 | AN36: 0.0166
B37: Lâm Việt | C37: LHG | D37: NA | E37: 47300 | F37: 622 | I37: 260 | L37: 5194 | O37: 37432 | R37: 0.0767 | U37: 0.1388 | X37: =IF(OR(COUNTBLANK(A_Entry_Forecast[[#This Row],[REV_FY]])<>0,COUNTBLANK(A_Entry_Forecast[[#This Row],[REV_FY+1]])<>0),"N","Y") -> N | AE37: =VLOOKUP(A_Entry_Forecast[[#This Row],[Ticker]],[1]!A_Entry_Data[#Data],2,FALSE) -> 33350 | AF37: =IF(A_Entry_Forecast[[#This Row],[Target Price]]<>0,A_Entry_Forecast[[#This Row],[Target Price]]/AE37-1,"") -> 0.41829085 | AH37: NVL | AI37: 4758.9018 | AJ37: 804.99023 | AK37: 413 | AL37: 19612.42 | AM37: 0.0032 | AN37: 0.0181
B38: Lâm Việt | C38: PHR | D38: HOLD | E38: 64800 | F38: 1645.8422 | G38: 1834.8719 | I38: 540.41102 | J38: 576.01554 | L38: 3988.2968 | M38: 4251.0624 | O38: 27756.872 | P38: 29007.934 | R38: 0.0786555 | S38: 0.086016352 | U38: 0.13753907 | V38: 0.1405374 | X38: =IF(OR(COUNTBLANK(A_Entry_Forecast[[#This Row],[REV_FY]])<>0,COUNTBLANK(A_Entry_Forecast[[#This Row],[REV_FY+1]])<>0),"N","Y") -> Y | AE38: =VLOOKUP(A_Entry_Forecast[[#This Row],[Ticker]],[1]!A_Entry_Data[#Data],2,FALSE) -> 62800 | AF38: =IF(A_Entry_Forecast[[#This Row],[Target Price]]<>0,A_Entry_Forecast[[#This Row],[Target Price]]/AE38-1,"") -> 0.031847134 | AH38: KDH | AI38: 2093.4939 | AJ38: 716.89414 | AK38: 840 | AL38: 16829.5 | AM38: 0.0299 | AN38: 0.0584
B39: Lâm Việt | C39: SZC | D39: BUY | E39: 45000 | F39: 1670.2676 | G39: 1743.6866 | I39: 661.77403 | J39: 759.69736 | L39: 3676.5228 | M39: 4220.5414 | O39: 22650.295 | P39: 26870.836 | R39: 0.06441227 | S39: 0.068991767 | U39: 0.16231677 | V39: 0.15706773 | X39: =IF(OR(COUNTBLANK(A_Entry_Forecast[[#This Row],[REV_FY]])<>0,COUNTBLANK(A_Entry_Forecast[[#This Row],[REV_FY+1]])<>0),"N","Y") -> Y | AE39: =VLOOKUP(A_Entry_Forecast[[#This Row],[Ticker]],[1]!A_Entry_Data[#Data],2,FALSE) -> 38100 | AF39: =IF(A_Entry_Forecast[[#This Row],[Target Price]]<>0,A_Entry_Forecast[[#This Row],[Target Price]]/AE39-1,"") -> 0.18110236 | AH39: NLG | AI39: 3181.4218 | AJ39: 483.7364 | AK39: 1185 | AL39: 24386.08 | AM39: 0.0174 | AN39: 0.0871
B40: Lâm Việt | C40: SIP | D40: NA | F40: 7479.2023 | G40: 7703.5783 | I40: 1324.4627 | J40: 1348.164 | L40: 14570.546 | M40: 14831.287 | O40: 49349.294 | P40: 55180.171 | X40: =IF(OR(COUNTBLANK(A_Entry_Forecast[[#This Row],[REV_FY]])<>0,COUNTBLANK(A_Entry_Forecast[[#This Row],[REV_FY+1]])<>0),"N","Y") -> Y | AE40: =VLOOKUP(A_Entry_Forecast[[#This Row],[Ticker]],[1]!A_Entry_Data[#Data],2,FALSE) -> 66500 | AF40: =IF(A_Entry_Forecast[[#This Row],[Target Price]]<>0,A_Entry_Forecast[[#This Row],[Target Price]]/AE40-1,"") | AH40: VHM | AI40: 103334.07 | AJ40: 33125.469 | AK40: 7607 | AL40: 41116.18 | AM40: 0.0819 | AN40: 0.2053
B41: Lâm Việt | C41: DPR | D41: HOLD | E41: 49700 | F41: 1334.8685 | G41: 1385.4156 | I41: 290.58575 | J41: 317.98512 | L41: 3344.4511 | M41: 3659.7999 | O41: 27521.624 | P41: 28181.424 | R41: 0.059594156 | S41: 0.056648538 | U41: 0.093872926 | V41: 0.10085641 | X41: =IF(OR(COUNTBLANK(A_Entry_Forecast[[#This Row],[REV_FY]])<>0,COUNTBLANK(A_Entry_Forecast[[#This Row],[REV_FY+1]])<>0),"N","Y") -> Y | AE41: =VLOOKUP(A_Entry_Forecast[[#This Row],[Ticker]],[1]!A_Entry_Data[#Data],2,FALSE) -> 42000 | AF41: =IF(A_Entry_Forecast[[#This Row],[Target Price]]<>0,A_Entry_Forecast[[#This Row],[Target Price]]/AE41-1,"") -> 0.18333333 | AH41: VRE | AI41: 9791.335 | AJ41: 4408.6 | AK41: 0 | AL41: 16232.94 | AM41: 0.0976 | AN41: 0.1239
B42: Lâm Việt | C42: NTC | D42: NA | X42: =IF(OR(COUNTBLANK(A_Entry_Forecast[[#This Row],[REV_FY]])<>0,COUNTBLANK(A_Entry_Forecast[[#This Row],[REV_FY+1]])<>0),"N","Y") -> N | AE42: =VLOOKUP(A_Entry_Forecast[[#This Row],[Ticker]],[1]!A_Entry_Data[#Data],2,FALSE) -> 174100 | AF42: =IF(A_Entry_Forecast[[#This Row],[Target Price]]<>0,A_Entry_Forecast[[#This Row],[Target Price]]/AE42-1,"")
B43: Nguyễn Thị Cẩm Tú | C43: KBC | D43: NA | E43: 35000 | F43: 5949.2776 | G43: 14924.701 | I43: 1352.2906 | J43: 5371.3018 | L43: 1761.7017 | M43: 6997.4837 | O43: 29131.542 | P43: 36867.485 | R43: 0.034925544 | S43: 0.11364844 | U43: 0.060474029 | V43: 0.18980095 | X43: =IF(OR(COUNTBLANK(A_Entry_Forecast[[#This Row],[REV_FY]])<>0,COUNTBLANK(A_Entry_Forecast[[#This Row],[REV_FY+1]])<>0),"N","Y") -> Y
C44: PLX | D44: HOLD | X44: N | AE44: =VLOOKUP(A_Entry_Forecast[[#This Row],[Ticker]],[1]!A_Entry_Data[#Data],2,FALSE) -> 38500 | AF44: =IF(A_Entry_Forecast[[#This Row],[Target Price]]<>0,A_Entry_Forecast[[#This Row],[Target Price]]/AE44-1,"") | AH44: DCM | AI44: 12601.812 | AJ44: 1107.088 | AK44: 1853 | AL44: 18824.33 | AM44: 0.0752 | AN44: 0.1079
C45: OIL | D45: HOLD | X45: N | AE45: =VLOOKUP(A_Entry_Forecast[[#This Row],[Ticker]],[1]!A_Entry_Data[#Data],2,FALSE) -> 12600 | AF45: =IF(A_Entry_Forecast[[#This Row],[Target Price]]<>0,A_Entry_Forecast[[#This Row],[Target Price]]/AE45-1,"") | AH45: DGC | AI45: 9747.9413 | AJ45: 3108.7533 | AK45: 7695 | AL45: 30531.18 | AM45: 0.2152 | AN45: 0.2949
B46: Lưu Thuỳ Linh | C46: PLC | D46: HOLD | F46: 7261.0115 | G46: 7392.4131 | I46: 118.5371 | J46: 125.51367 | L46: 1445.9693 | M46: 1552.5218 | O46: 14917.599 | P46: 14470.121 | R46: 0.023314333 | S46: 0.032362262 | U46: 0.096930432 | V46: 0.10729156 | X46: N | AE46: =VLOOKUP(A_Entry_Forecast[[#This Row],[Ticker]],[1]!A_Entry_Data[#Data],2,FALSE) -> 29100 | AF46: =IF(A_Entry_Forecast[[#This Row],[Target Price]]<>0,A_Entry_Forecast[[#This Row],[Target Price]]/AE46-1,"") | AH46: DPM | AI46: 13569.186 | AJ46: 532.67386 | AK46: 1063 | AL46: 29084.34 | AM46: 0.0343 | AN46: 0.0431
B47: Lưu Thuỳ Linh | C47: DGC | D47: HOLD | E47: 109300 | F47: 10871.374 | G47: 12202.871 | I47: 3488.3822 | J47: 3865.038 | L47: 9185.2882 | M47: 10177.064 | O47: 42822.955 | P47: 50645.073 | R47: 0.21775575 | S47: 0.20664111 | U47: 0.24761975 | V47: 0.23153104 | X47: Y | Y47: 4392.1064 | Z47: 4948.5983 | AB47: -11791.397 | AC47: -14642.69 | AE47: =VLOOKUP(A_Entry_Forecast[[#This Row],[Ticker]],[1]!A_Entry_Data[#Data],2,FALSE) -> 107900 | AF47: =IF(A_Entry_Forecast[[#This Row],[Target Price]]<>0,A_Entry_Forecast[[#This Row],[Target Price]]/AE47-1,"") -> 0.012974977 | AH47: DRC | AI47: 4495.1745 | AJ47: 247.74095 | AK47: 2085 | AL47: 15596.8 | AM47: 0.0726 | AN47: 0.1317
B48: Lưu Thuỳ Linh | C48: CSV | D48: HOLD | F48: 1987 | G48: 2086.35 | I48: 247 | J48: 266.76 | L48: 2235.2959 | M48: 2414.1196 | O48: 14063.51 | P48: 14204.145 | R48: 0.13286713 | S48: 0.1434965 | U48: 0.15894296 | V48: 0.16995881 | X48: Y | AE48: =VLOOKUP(A_Entry_Forecast[[#This Row],[Ticker]],[1]!A_Entry_Data[#Data],2,FALSE) -> 37050 | AF48: =IF(A_Entry_Forecast[[#This Row],[Target Price]]<>0,A_Entry_Forecast[[#This Row],[Target Price]]/AE48-1,"") | AH48: QTP | AI48: 12058.194 | AJ48: 614.46824 | AK48: 1365 | AL48: 11480.73 | AM48: 0.0796 | AN48: 0.1085
B49: Lưu Thuỳ Linh | C49: DCM | D49: BUY | E49: 47300 | F49: 19929.562 | G49: 19723.883 | I49: 2845.4463 | J49: 2621.1106 | L49: 4031.1385 | M49: 3713.3226 | O49: 22175.856 | P49: 25128.718 | R49: 0.16807406 | S49: 0.13888075 | U49: 0.24229828 | V49: 0.19697508 | X49: Y | Y49: 3217.9451 | Z49: 2923.0538 | AB49: -7882.4425 | AC49: -8584.4802
B50: Lưu Thuỳ Linh | C50: DPM | D50: HOLD | E50: 30500 | F50: 17284.032 | G50: 17273.084 | I50: 1381.333 | J50: 1120.5364 | L50: 1905.1342 | M50: 1705.5138 | O50: 22340.519 | P50: 21949.592 | R50: 0.069828445 | S50: 0.048515527 | U50: 0.090927708 | V50: 0.07507419 | X50: Y | Y50: 1762.4422 | Z50: 1393.9117 | AB50: -6348.823 | AC50: -7271.7431 | AE50: =VLOOKUP(A_Entry_Forecast[[#This Row],[Ticker]],[1]!A_Entry_Data[#Data],2,FALSE) -> 28800 | AF50: =IF(A_Entry_Forecast[[#This Row],[Target Price]]<>0,A_Entry_Forecast[[#This Row],[Target Price]]/AE50-1,"") -> 0.059027778 | AH50: BWE | AI50: 3525.8858 | AJ50: 671.559 | AK50: 2889 | AL50: 24876.22 | AM50: 0.0608 | AN50: 0.1462
B51: Lưu Thuỳ Linh | C51: DDV | D51: BUY | E51: 38200 | F51: 5696.7889 | G51: 5141.5633 | I51: 485.61948 | J51: 476.58296 | L51: 3323.659 | M51: 3261.8116 | O51: 12232.17 | P51: 15065.588 | R51: 0.27171459 | S51: 0.21650742 | U51: 0.21240671 | V51: 0.19266528 | X51: Y | Y51: 3323.659 | Z51: 3261.8116 | AE51: =VLOOKUP(A_Entry_Forecast[[#This Row],[Ticker]],[1]!A_Entry_Data[#Data],2,FALSE) -> 34800 | AF51: =IF(A_Entry_Forecast[[#This Row],[Target Price]]<>0,A_Entry_Forecast[[#This Row],[Target Price]]/AE51-1,"") -> 0.097701149 | AH51: DHC | AI51: 3258.9085 | AJ51: 309.08135 | AK51: 3840 | AL51: 22966.25 | AM51: 0.1066 | AN51: 0.1719
B52: Lưu Thuỳ Linh | C52: DRC | D52: HOLD | F52: 4803.5805 | G52: 5052.3286 | I52: 108.71932 | J52: 191.47113 | L52: 648.81072 | M52: 1142.6536 | O52: 15519.442 | P52: 16266.178 | R52: 0.025495719 | S52: 0.043462167 | U52: 0.044973208 | V52: 0.075598331 | X52: Y | Y52: 317.41028 | Z52: 373.97998 | AB52: -132.53742 | AC52: -407.9615 | AE52: =VLOOKUP(A_Entry_Forecast[[#This Row],[Ticker]],[1]!A_Entry_Data[#Data],2,FALSE) -> 17600 | AF52: =IF(A_Entry_Forecast[[#This Row],[Target Price]]<>0,A_Entry_Forecast[[#This Row],[Target Price]]/AE52-1,"") | AH52: NT2 | AI52: 6382.5991 | AJ52: 495.78759 | AK52: 1624 | AL52: 15140.41 | AM52: 0.0623 | AN52: 0.1105
B53: Lưu Thuỳ Linh | C53: CSM | D53: HOLD | E53: 13500 | F53: 4799.7848 | G53: 4903.4517 | I53: 73.001339 | J53: 93.42625 | L53: 520.63913 | M53: 666.3078 | O53: 13922.444 | P53: 14568.864 | R53: 0.037447404 | S53: 0.043256938 | U53: 0.050599317 | V53: 0.061883167 | X53: Y | Y53: 370.11106 | Z53: 378.65181 | AB53: 1499.6384 | AC53: 1259.0386
B54: Lưu Thuỳ Linh | C54: BSR | D54: HOLD | E54: 20100 | F54: 109209 | G54: 140582 | H54: 150133 | I54: 1196 | J54: 1293 | K54: 1473 | L54: 386 | M54: 417 | N54: 475 | O54: 19100 | P54: 20300 | R54: 0.05 | S54: 0.05 | U54: 0.08 | V54: 0.08 | X54: =IF(OR(COUNTBLANK(A_Entry_Forecast[[#This Row],[REV_FY]])<>0,COUNTBLANK(A_Entry_Forecast[[#This Row],[REV_FY+1]])<>0),"N","Y") -> Y | AE54: =VLOOKUP(A_Entry_Forecast[[#This Row],[Ticker]],[1]!A_Entry_Data[#Data],2,FALSE) -> 22950 | AF54: =IF(A_Entry_Forecast[[#This Row],[Target Price]]<>0,A_Entry_Forecast[[#This Row],[Target Price]]/AE54-1,"") -> -0.12418301 | AH54: FRT | AI54: 31849.65 | AJ54: -345.64349 | AK54: -2537 | AL54: 11738.32 | AM54: -0.0293 | AN54: -0.1825
B55: Lưu Thuỳ Linh | C55: PVD | D55: BUY | E55: 23700 | F55: 8963 | G55: 9983 | I55: 710 | J55: 883 | L55: 1265 | M55: 1484 | O55: 28700 | P55: 29200 | R55: 0.041 | S55: 0.04 | U55: 0.06 | V55: 0.06 | X55: =IF(OR(COUNTBLANK(A_Entry_Forecast[[#This Row],[REV_FY]])<>0,COUNTBLANK(A_Entry_Forecast[[#This Row],[REV_FY+1]])<>0),"N","Y") -> Y | AE55: =VLOOKUP(A_Entry_Forecast[[#This Row],[Ticker]],[1]!A_Entry_Data[#Data],2,FALSE) -> 23000 | AF55: =IF(A_Entry_Forecast[[#This Row],[Target Price]]<>0,A_Entry_Forecast[[#This Row],[Target Price]]/AE55-1,"") -> 0.030434783 | AH55: MSN | AI55: 78251.619 | AJ55: 418.695 | AK55: 294 | AL55: 18562.19 | AM55: 0.0029 | AN55: 0.0709
B56: n/a | C56: QNS | D56: HOLD | X56: =IF(OR(COUNTBLANK(A_Entry_Forecast[[#This Row],[REV_FY]])<>0,COUNTBLANK(A_Entry_Forecast[[#This Row],[REV_FY+1]])<>0),"N","Y") -> N | AE56: =VLOOKUP(A_Entry_Forecast[[#This Row],[Ticker]],[1]!A_Entry_Data[#Data],2,FALSE) -> 49300 | AF56: =IF(A_Entry_Forecast[[#This Row],[Target Price]]<>0,A_Entry_Forecast[[#This Row],[Target Price]]/AE56-1,"") | AH56: PC1 | AI56: 7803.0082 | AJ56: 136.56999 | AK56: 395 | AL56: 16665.2 | AM56: 0.0065 | AN56: 0.0576
B57: n/a | C57: SAB | D57: NA | X57: =IF(OR(COUNTBLANK(A_Entry_Forecast[[#This Row],[REV_FY]])<>0,COUNTBLANK(A_Entry_Forecast[[#This Row],[REV_FY+1]])<>0),"N","Y") -> N | AE57: =VLOOKUP(A_Entry_Forecast[[#This Row],[Ticker]],[1]!A_Entry_Data[#Data],2,FALSE) -> 48300 | AF57: =IF(A_Entry_Forecast[[#This Row],[Target Price]]<>0,A_Entry_Forecast[[#This Row],[Target Price]]/AE57-1,"") | AH57: POW | AI57: 27944.691 | AJ57: 1075.0479 | AK57: 459 | AL57: 13430.09 | AM57: 0.0169 | AN57: 0.0429
B58: n/a | C58: VSC | D58: HOLD | X58: =IF(OR(COUNTBLANK(A_Entry_Forecast[[#This Row],[REV_FY]])<>0,COUNTBLANK(A_Entry_Forecast[[#This Row],[REV_FY+1]])<>0),"N","Y") -> N | AE58: =VLOOKUP(A_Entry_Forecast[[#This Row],[Ticker]],[1]!A_Entry_Data[#Data],2,FALSE) -> 27700 | AF58: =IF(A_Entry_Forecast[[#This Row],[Target Price]]<>0,A_Entry_Forecast[[#This Row],[Target Price]]/AE58-1,"") | AH58: TDM | AI58: 532.57392 | AJ58: 283.44986 | AK58: 2680 | AL58: 20366.36 | AM58: 0.1132 | AN58: 0.139
B59: Nguyễn Dân Trưởng | C59: GEX | D59: HOLD | E59: 35100 | F59: 38136.903 | G59: 38892.552 | H59: 41187.559 | I59: 1129.6703 | J59: 1292.1494 | K59: 1490.2298 | L59: 1314.4872 | M59: 1503.5483 | N59: 1734.0352 | O59: 29923.46 | P59: 32823.469 | Q59: 36106.78 | R59: 0.045397963 | S59: 0.044737672 | T59: 0.04644563 | U59: 0.089012451 | V59: 0.095088397 | W59: 0.094984282 | X59: =IF(OR(COUNTBLANK(A_Entry_Forecast[[#This Row],[REV_FY]])<>0,COUNTBLANK(A_Entry_Forecast[[#This Row],[REV_FY+1]])<>0),"N","Y") -> Y | AE59: =VLOOKUP(A_Entry_Forecast[[#This Row],[Ticker]],[1]!A_Entry_Data[#Data],2,FALSE) -> 58800 | AF59: =IF(A_Entry_Forecast[[#This Row],[Target Price]]<>0,A_Entry_Forecast[[#This Row],[Target Price]]/AE59-1,"") -> -0.40306122 | AH59: VEA | AI59: 3842.55 | AJ59: 6233.5826 | AK59: 4691 | AL59: 19213.2 | AM59: 0.2284 | AN59: 0.2493
B60: Nguyễn Dân Trưởng | C60: BWE | D60: HOLD | E60: 42100 | F60: 4262.7199 | G60: 4555.3088 | H60: 4987.7236 | I60: 695.96081 | J60: 884 | K60: 1041 | L60: 3164.8968 | M60: 4097.2114 | N60: 4817.2449 | O60: 27805.355 | P60: 31300.401 | Q60: 35388.528 | R60: 0.050910362 | S60: 0.065080959 | T60: 0.073364209 | U60: 0.1239787 | V60: 0.14248695 | W60: 0.14787861 | X60: =IF(OR(COUNTBLANK(A_Entry_Forecast[[#This Row],[REV_FY]])<>0,COUNTBLANK(A_Entry_Forecast[[#This Row],[REV_FY+1]])<>0),"N","Y") -> Y | AE60: =VLOOKUP(A_Entry_Forecast[[#This Row],[Ticker]],[1]!A_Entry_Data[#Data],2,FALSE) -> 49000 | AF60: =IF(A_Entry_Forecast[[#This Row],[Target Price]]<>0,A_Entry_Forecast[[#This Row],[Target Price]]/AE60-1,"") -> -0.14081633 | AH60: BMP | AI60: 5156.9844 | AJ60: 1041.0063 | AK60: 12717 | AL60: 32857.29 | AM60: 0.3305 | AN60: 0.392
B61: Nguyễn Dân Trưởng | C61: DHC | D61: BUY | E61: 35100 | F61: 3624.3448 | G61: 3714.0387 | H61: 4828.9331 | I61: 308.74048 | J61: 322.13148 | K61: 382.34583 | L61: 3196.0712 | M61: 3334.6944 | N61: 3958.0313 | O61: 22388.618 | P61: 25723.312 | Q61: 29681.344 | R61: 0.088286099 | S61: 0.083152035 | T61: 0.070885886 | U61: 0.14822838 | V61: 0.15917111 | W61: 0.14287721 | X61: =IF(OR(COUNTBLANK(A_Entry_Forecast[[#This Row],[REV_FY]])<>0,COUNTBLANK(A_Entry_Forecast[[#This Row],[REV_FY+1]])<>0),"N","Y") -> Y | AE61: =VLOOKUP(A_Entry_Forecast[[#This Row],[Ticker]],[1]!A_Entry_Data[#Data],2,FALSE) -> 32250 | AF61: =IF(A_Entry_Forecast[[#This Row],[Target Price]]<>0,A_Entry_Forecast[[#This Row],[Target Price]]/AE61-1,"") -> 0.088372093
B62: Nguyễn Dân Trưởng | C62: HDG | D62: BUY | E62: 33100 | F62: 3200.3596 | G62: 3675.3972 | H62: 8237.3129 | I62: 882.56169 | J62: 1337.736 | K62: 1579.9154 | L62: 2624.3286 | M62: 3977.8055 | N62: 4697.9347 | O62: 25150.473 | P62: 29813.373 | Q62: 35232.239 | R62: 0.076298339 | S62: 0.097990445 | T62: 0.093494402 | U62: 0.13494248 | V62: 0.17485763 | W62: 0.17344068 | X62: =IF(OR(COUNTBLANK(A_Entry_Forecast[[#This Row],[REV_FY]])<>0,COUNTBLANK(A_Entry_Forecast[[#This Row],[REV_FY+1]])<>0),"N","Y") -> Y | AE62: =VLOOKUP(A_Entry_Forecast[[#This Row],[Ticker]],[1]!A_Entry_Data[#Data],2,FALSE) -> 28800 | AF62: =IF(A_Entry_Forecast[[#This Row],[Target Price]]<>0,A_Entry_Forecast[[#This Row],[Target Price]]/AE62-1,"") -> 0.14930556 | AH62: HSG | AI62: 32806.456 | AJ62: 813.60136 | AK62: 0 | AL62: 17621.4 | AM62: 0.0017 | AN62: 0.0028
B63: Nguyễn Dân Trưởng | C63: NT2 | D63: HOLD | E63: 25300 | F63: 7381.2259 | G63: 7559.6851 | H63: 7909.2252 | I63: 528.85739 | J63: 724.74411 | K63: 852.89907 | L63: 1837.1012 | M63: 2517.5563 | N63: 2962.7304 | O63: 17388.761 | P63: 21406.286 | Q63: 24369.016 | R63: 0.055877451 | S63: 0.067156397 | T63: 0.071559491 | U63: 0.11503292 | V63: 0.12978751 | W63: 0.12944668 | X63: =IF(OR(COUNTBLANK(A_Entry_Forecast[[#This Row],[REV_FY]])<>0,COUNTBLANK(A_Entry_Forecast[[#This Row],[REV_FY+1]])<>0),"N","Y") -> Y | AE63: =VLOOKUP(A_Entry_Forecast[[#This Row],[Ticker]],[1]!A_Entry_Data[#Data],2,FALSE) -> 22450 | AF63: =IF(A_Entry_Forecast[[#This Row],[Target Price]]<>0,A_Entry_Forecast[[#This Row],[Target Price]]/AE63-1,"") -> 0.12694878 | AH63: HT1 | AI63: 7049.0261 | AJ63: 16.918176 | AK63: 44 | AL63: 12638.07 | AM63: 0.0019 | AN63: 0.0035
B64: Nguyễn Dân Trưởng | C64: QTP | D64: BUY | E64: 12900 | F64: 12106.81 | G64: 12129.313 | H64: 12152.04 | I64: 783.61944 | J64: 724.08522 | K64: 746.7651 | L64: 1741.3765 | M64: 1609.0783 | N64: 1659.478 | O64: 11500 | P64: 11700 | Q64: 11800 | R64: 0.10686118 | S64: 0.098462112 | T64: 0.10082591 | U64: 0.15244596 | V64: 0.13873591 | W64: 0.14144384 | X64: =IF(OR(COUNTBLANK(A_Entry_Forecast[[#This Row],[REV_FY]])<>0,COUNTBLANK(A_Entry_Forecast[[#This Row],[REV_FY+1]])<>0),"N","Y") -> Y | AE64: =VLOOKUP(A_Entry_Forecast[[#This Row],[Ticker]],[1]!A_Entry_Data[#Data],2,FALSE) -> 13200 | AF64: =IF(A_Entry_Forecast[[#This Row],[Target Price]]<>0,A_Entry_Forecast[[#This Row],[Target Price]]/AE64-1,"") -> -0.022727273 | AH64: KBC | AI64: 5644.6629 | AJ64: 1995.5561 | AK64: 2600 | AL64: 23633.02 | AM64: 0.0584 | AN64: 0.1297
B65: Nguyễn Dân Trưởng | C65: PC1 | D65: BUY | E65: 26700 | F65: 12788.225 | G65: 14525.777 | H65: 14075.298 | I65: 559.2402 | J65: 1157.3368 | K65: 1191.2799 | L65: 1563.8708 | M65: 3236.4004 | N65: 3331.3195 | O65: 23760.341 | P65: 27864.524 | Q65: 32187.13 | R65: 0.03595861 | S65: 0.066343784 | T65: 0.069535407 | U65: 0.096304461 | V65: 0.15900027 | W65: 0.14396293 | X65: =IF(OR(COUNTBLANK(A_Entry_Forecast[[#This Row],[REV_FY]])<>0,COUNTBLANK(A_Entry_Forecast[[#This Row],[REV_FY+1]])<>0),"N","Y") -> Y | AE65: =VLOOKUP(A_Entry_Forecast[[#This Row],[Ticker]],[1]!A_Entry_Data[#Data],2,FALSE) -> 28200 | AF65: =IF(A_Entry_Forecast[[#This Row],[Target Price]]<>0,A_Entry_Forecast[[#This Row],[Target Price]]/AE65-1,"") -> -0.053191489 | AH65: NKG | AI65: 18595.974 | AJ65: 117.40857 | AK65: 0 | AL65: 20598.3 | AM65: 0.0091 | AN65: 0.0219
B66: Nguyễn Dân Trưởng | C66: POW | D66: BUY | E66: 17700 | F66: 41988.326 | G66: 60550.125 | H66: 64045.798 | I66: 1562.5086 | J66: 2122.3378 | K66: 1450.2711 | L66: 667.22548 | M66: 906.28481 | N66: 619.2976 | O66: 15512.888 | P66: 16573.314 | Q66: 17339.075 | R66: 0.021695892 | S66: 0.027015317 | T66: 0.019369858 | U66: 0.052331989 | V66: 0.066098564 | W66: 0.045161139 | X66: =IF(OR(COUNTBLANK(A_Entry_Forecast[[#This Row],[REV_FY]])<>0,COUNTBLANK(A_Entry_Forecast[[#This Row],[REV_FY+1]])<>0),"N","Y") -> Y | AE66: =VLOOKUP(A_Entry_Forecast[[#This Row],[Ticker]],[1]!A_Entry_Data[#Data],2,FALSE) -> 16150 | AF66: =IF(A_Entry_Forecast[[#This Row],[Target Price]]<>0,A_Entry_Forecast[[#This Row],[Target Price]]/AE66-1,"") -> 0.095975232 | AH66: BCC | AI66: 3081.3654 | AJ66: -193.68268 | AK66: -1572 | AL66: 15045.48 | AM66: -0.0499 | AN66: -0.0997
B67: Nguyễn Dân Trưởng | C67: REE | D67: HOLD | E67: 67300 | F67: 10132.351 | G67: 12098.999 | H67: 11964.368 | I67: 2486.9169 | J67: 3043 | K67: 3954 | L67: 5279.4188 | M67: 6556.7218 | N67: 8560.2304 | O67: 54200.079 | P67: 62262.309 | Q67: 72410.526 | R67: 0.08300492 | S67: 0.096570825 | T67: 0.11199138 | U67: 0.12821127 | V67: 0.13845208 | W67: 0.15070919 | X67: =IF(OR(COUNTBLANK(A_Entry_Forecast[[#This Row],[REV_FY]])<>0,COUNTBLANK(A_Entry_Forecast[[#This Row],[REV_FY+1]])<>0),"N","Y") -> Y | AE67: =VLOOKUP(A_Entry_Forecast[[#This Row],[Ticker]],[1]!A_Entry_Data[#Data],2,FALSE) -> 68600 | AF67: =IF(A_Entry_Forecast[[#This Row],[Target Price]]<>0,A_Entry_Forecast[[#This Row],[Target Price]]/AE67-1,"") -> -0.018950437 | AH67: VGC | AI67: 13193.818 | AJ67: 1218.0731 | AK67: 0 | AL67: 17515.77 | AM67: 0.0518 | AN67: 0.1503
B68: Nguyễn Dân Trưởng | C68: VEA | D68: HOLD | E68: 41500 | F68: 4321.0147 | G68: 4387.8945 | H68: 4429.4507 | I68: 7293.4831 | J68: 7444.501 | K68: 7541.2654 | L68: 5488.7742 | M68: 5602.424 | N68: 5675.2449 | O68: 19802.284 | P68: 19860.106 | Q68: 19918.68 | R68: 0.26691027 | S68: 0.27156914 | T68: 0.2742811 | U68: 0.28044071 | V68: 0.28542133 | W68: 0.28828525 | X68: =IF(OR(COUNTBLANK(A_Entry_Forecast[[#This Row],[REV_FY]])<>0,COUNTBLANK(A_Entry_Forecast[[#This Row],[REV_FY+1]])<>0),"N","Y") -> Y | AE68: =VLOOKUP(A_Entry_Forecast[[#This Row],[Ticker]],[1]!A_Entry_Data[#Data],2,FALSE) -> 39300 | AF68: =IF(A_Entry_Forecast[[#This Row],[Target Price]]<>0,A_Entry_Forecast[[#This Row],[Target Price]]/AE68-1,"") -> 0.055979644 | AH68: DBC | AI68: 11110.001 | AJ68: 25.007194 | AK68: 103 | AL68: 19281.81 | AM68: 0.0019 | AN68: 0.0054
B69: Nguyễn Dân Trưởng | C69: VGC | D69: HOLD | E69: 46100 | F69: 12419.734 | G69: 12210.714 | H69: 13665.983 | I69: 1109.826 | J69: 1068.29 | K69: 1113.5523 | L69: 2475.0803 | M69: 2382.4488 | N69: 2483.3905 | O69: 24110.108 | P69: 26754.251 | Q69: 29465.529 | R69: 0.050983535 | S69: 0.044888866 | T69: 0.043812189 | U69: 0.12437947 | V69: 0.10396839 | W69: 0.096452823 | X69: =IF(OR(COUNTBLANK(A_Entry_Forecast[[#This Row],[REV_FY]])<>0,COUNTBLANK(A_Entry_Forecast[[#This Row],[REV_FY+1]])<>0),"N","Y") -> Y | AE69: =VLOOKUP(A_Entry_Forecast[[#This Row],[Ticker]],[1]!A_Entry_Data[#Data],2,FALSE) -> 66300 | AF69: =IF(A_Entry_Forecast[[#This Row],[Target Price]]<>0,A_Entry_Forecast[[#This Row],[Target Price]]/AE69-1,"") -> -0.30467572 | AH69: DGW | AI69: 18817.475 | AJ69: 354.3891 | AK69: 2123 | AL69: 15515.86 | AM69: 0.0512 | AN69: 0.1454
B70: Nguyễn Thị Cẩm Tú | C70: PVS | D70: BUY | E70: 38600 | F70: 36151 | G70: 43138 | H70: 20213 | I70: 1177 | J70: 1061 | K70: 1246 | L70: 1847 | M70: 1665 | N70: 1955 | O70: 27850 | P70: 30060 | R70: 0.047 | S70: 0.04 | T70: 0.037 | U70: 0.09 | V70: 0.08 | W70: 0.08 | X70: =IF(OR(COUNTBLANK(A_Entry_Forecast[[#This Row],[REV_FY]])<>0,COUNTBLANK(A_Entry_Forecast[[#This Row],[REV_FY+1]])<>0),"N","Y") -> Y | AE70: =VLOOKUP(A_Entry_Forecast[[#This Row],[Ticker]],[1]!A_Entry_Data[#Data],2,FALSE) -> 37900 | AF70: =IF(A_Entry_Forecast[[#This Row],[Target Price]]<>0,A_Entry_Forecast[[#This Row],[Target Price]]/AE70-1,"") -> 0.018469657 | AH70: MWG | AI70: 118279.79 | AJ70: 167.66939 | AK70: 115 | AL70: 15953.62 | AM70: 0.0029 | AN70: 0.0071
B71: Nguyễn Thị Cẩm Tú | C71: GAS | D71: BUY | E71: 80200 | F71: 108710 | G71: 119613 | H71: 122242 | I71: 13131 | J71: 12278 | K71: 12620 | L71: 5605 | M71: 5241 | N71: 5387 | O71: 26696 | P71: 27887 | R71: 0.15 | S71: 0.15 | T71: 0.15 | U71: 0.18 | V71: 0.16 | W71: 0.16 | X71: =IF(OR(COUNTBLANK(A_Entry_Forecast[[#This Row],[REV_FY]])<>0,COUNTBLANK(A_Entry_Forecast[[#This Row],[REV_FY+1]])<>0),"N","Y") -> Y | AE71: =VLOOKUP(A_Entry_Forecast[[#This Row],[Ticker]],[1]!A_Entry_Data[#Data],2,FALSE) -> 70500 | AF71: =IF(A_Entry_Forecast[[#This Row],[Target Price]]<>0,A_Entry_Forecast[[#This Row],[Target Price]]/AE71-1,"") -> 0.13758865 | AH71: PNJ | AI71: 33136.929 | AJ71: 1971.4841 | AK71: 5435 | AL71: 29882.65 | AM71: 0.142 | AN71: 0.216
B72: Nguyễn Thị Cẩm Tú | C72: PVB | D72: BUY | E72: 38700 | F72: 480 | G72: 1510 | I72: 56 | J72: 163 | L72: 2464 | M72: 7175 | O72: 21806 | P72: 28900 | R72: 0.03 | S72: 0.13 | U72: 0.11 | V72: 0.28 | X72: =IF(OR(COUNTBLANK(A_Entry_Forecast[[#This Row],[REV_FY]])<>0,COUNTBLANK(A_Entry_Forecast[[#This Row],[REV_FY+1]])<>0),"N","Y") -> Y | AE72: =VLOOKUP(A_Entry_Forecast[[#This Row],[Ticker]],[1]!A_Entry_Data[#Data],2,FALSE) -> 30800 | AF72: =IF(A_Entry_Forecast[[#This Row],[Target Price]]<>0,A_Entry_Forecast[[#This Row],[Target Price]]/AE72-1,"") -> 0.25649351 | AH72: VTP | AI72: 19589.873 | AJ72: 380.2438 | AK72: 2654 | AL72: 12986.17 | AM72: 0.0608 | AN72: 0.2559
B73: Phạm Quang Minh | C73: HPG | D73: BUY | E73: 32300 | F73: 173016.07 | G73: 217293.39 | I73: 15816.642 | J73: 22693.427 | L73: 2472.7938 | M73: 3547.9189 | O73: 20395.985 | P73: 23942.561 | R73: 0.063580475 | S73: 0.07601043 | U73: 0.12123924 | V73: 0.1481846 | X73: =IF(OR(COUNTBLANK(A_Entry_Forecast[[#This Row],[REV_FY]])<>0,COUNTBLANK(A_Entry_Forecast[[#This Row],[REV_FY+1]])<>0),"N","Y") -> Y
B74: Phạm Quang Minh | C74: HSG | D74: HOLD | E74: 19900 | F74: 37911.723 | G74: 39852.355 | I74: 740.81612 | J74: 705.14803 | L74: 1192.9746 | M74: 1135.5364 | O74: 18767.305 | P74: 19906.005 | R74: 0.036596329 | S74: 0.033242791 | U74: 0.063569697 | V74: 0.057047797 | X74: =IF(OR(COUNTBLANK(A_Entry_Forecast[[#This Row],[REV_FY]])<>0,COUNTBLANK(A_Entry_Forecast[[#This Row],[REV_FY+1]])<>0),"N","Y") -> Y | AE74: =VLOOKUP(A_Entry_Forecast[[#This Row],[Ticker]],[1]!A_Entry_Data[#Data],2,FALSE) -> 19850 | AF74: =IF(A_Entry_Forecast[[#This Row],[Target Price]]<>0,A_Entry_Forecast[[#This Row],[Target Price]]/AE74-1,"") -> 0.0025188917 | AH74: PVT | AI74: 9487.0019 | AJ74: 980.2501 | AK74: 3029 | AL74: 22879.05 | AM74: 0.0618 | AN74: 0.1848
B75: Phạm Quang Minh | C75: NKG | D75: HOLD | E75: 14400 | F75: 16996.155 | G75: 29707.736 | I75: 300.58269 | J75: 256.00341 | L75: 671.58678 | M75: 571.98406 | O75: 14378.208 | P75: 14950.192 | R75: 0.019066949 | S75: 0.010993628 | U75: 0.046708658 | V75: 0.038253596 | X75: =IF(OR(COUNTBLANK(A_Entry_Forecast[[#This Row],[REV_FY]])<>0,COUNTBLANK(A_Entry_Forecast[[#This Row],[REV_FY+1]])<>0),"N","Y") -> Y | AE75: 54000 | AF75: =IF(A_Entry_Forecast[[#This Row],[Target Price]]<>0,A_Entry_Forecast[[#This Row],[Target Price]]/AE75-1,"") -> -0.73333333 | AH75: QNS | AI75: 10022.844 | AJ75: 2189.4778 | AK75: 7192 | AL75: 24056.07 | AM75: 0.1961 | AN75: 0.2728
B76: Phạm Quang Minh | C76: NTP | D76: HOLD | E76: 66000 | F76: 6448.4827 | G76: 7093.331 | I76: 957.08259 | J76: 1070.982 | L76: 6064.5022 | M76: 7513.9611 | O76: 31528.867 | P76: 38133.734 | R76: 0.12248285 | S76: 0.11896107 | U76: 0.2129746 | V76: 0.19704236 | X76: =IF(OR(COUNTBLANK(A_Entry_Forecast[[#This Row],[REV_FY]])<>0,COUNTBLANK(A_Entry_Forecast[[#This Row],[REV_FY+1]])<>0),"N","Y") -> Y | AE76: =VLOOKUP(A_Entry_Forecast[[#This Row],[Ticker]],[1]!A_Entry_Data[#Data],2,FALSE) -> 65600 | AF76: =IF(A_Entry_Forecast[[#This Row],[Target Price]]<>0,A_Entry_Forecast[[#This Row],[Target Price]]/AE76-1,"") -> 0.006097561 | AH76: SAB | AI76: 30461.367 | AJ76: 4117.6051 | AK76: 3132 | AL76: 18878.08 | AM76: 0.1202 | AN76: 0.1797
B77: Phạm Quang Minh | C77: CTD | D77: BUY | E77: 96200 | F77: 24866.699 | G77: 29750 | I77: 453.83784 | J77: 433.18357 | L77: 4541.5569 | M77: 4334.8695 | O77: 89690.771 | P77: 94012.643 | R77: 0.01534117 | S77: 0.013599236 | U77: 0.050635721 | V77: 0.046109432 | X77: =IF(OR(COUNTBLANK(A_Entry_Forecast[[#This Row],[REV_FY]])<>0,COUNTBLANK(A_Entry_Forecast[[#This Row],[REV_FY+1]])<>0),"N","Y") -> Y | AE77: =VLOOKUP(A_Entry_Forecast[[#This Row],[Ticker]],[1]!A_Entry_Data[#Data],2,FALSE) -> 82700 | AF77: =IF(A_Entry_Forecast[[#This Row],[Target Price]]<>0,A_Entry_Forecast[[#This Row],[Target Price]]/AE77-1,"") -> 0.16324063 | AH77: SCS | AI77: 704.82515 | AJ77: 498.30731 | AK77: 0 | AL77: 12473.13 | AM77: 0.3058 | AN77: 0.3595
B78: Phạm Quang Minh | C78: BMP | D78: HOLD | E78: 151200 | F78: 5654.208 | G78: 5908.6474 | I78: 1237.4429 | J78: 1126.2411 | L78: 15116.403 | M78: 13757.979 | O78: 36119.934 | P78: 36877.913 | R78: 0.34840588 | S78: 0.30625167 | U78: 0.41850583 | V78: 0.37306827 | X78: =IF(OR(COUNTBLANK(A_Entry_Forecast[[#This Row],[REV_FY]])<>0,COUNTBLANK(A_Entry_Forecast[[#This Row],[REV_FY+1]])<>0),"N","Y") -> Y
B79: Phạm Thị Minh Châu | C79: BAF | D79: NA | F79: 4962 | G79: 5537 | I79: 525 | J79: 561 | L79: 2108 | M79: 2247 | O79: 14680 | P79: 16411 | R79: 0.045 | S79: 0.048 | U79: 0.103 | V79: 0.106 | X79: =IF(OR(COUNTBLANK(A_Entry_Forecast[[#This Row],[REV_FY]])<>0,COUNTBLANK(A_Entry_Forecast[[#This Row],[REV_FY+1]])<>0),"N","Y") -> Y
B80: Phạm Thị Minh Châu | C80: DBC | D80: BUY | E80: 32200 | F80: 15152 | G80: 16823 | I80: 1643 | J80: 1763 | L80: 3634 | M80: 3898 | O80: 24637 | P80: 29378 | R80: 0.1 | S80: 0.1 | U80: 0.19 | V80: 0.18 | X80: =IF(OR(COUNTBLANK(A_Entry_Forecast[[#This Row],[REV_FY]])<>0,COUNTBLANK(A_Entry_Forecast[[#This Row],[REV_FY+1]])<>0),"N","Y") -> Y | AE80: =VLOOKUP(A_Entry_Forecast[[#This Row],[Ticker]],[1]!A_Entry_Data[#Data],2,FALSE) -> 31250 | AF80: =IF(A_Entry_Forecast[[#This Row],[Target Price]]<>0,A_Entry_Forecast[[#This Row],[Target Price]]/AE80-1,"") -> 0.0304 | AH80: VNM | AI80: 60368.916 | AJ80: 8873.8124 | AK80: 3796 | AL80: 15166.26 | AM80: 0.1754 | AN80: 0.2931
B81: Phạm Thị Minh Châu | C81: DGW | D81: HOLD | E81: 52900 | F81: 24678 | G81: 27682 | I81: 530 | J81: 644 | L81: 2418 | M81: 2938 | O81: 15747 | P81: 18488 | R81: 0.06 | S81: 0.06 | U81: 0.15 | V81: 0.16 | X81: =IF(OR(COUNTBLANK(A_Entry_Forecast[[#This Row],[REV_FY]])<>0,COUNTBLANK(A_Entry_Forecast[[#This Row],[REV_FY+1]])<>0),"N","Y") -> Y | AE81: =VLOOKUP(A_Entry_Forecast[[#This Row],[Ticker]],[1]!A_Entry_Data[#Data],2,FALSE) -> 48150 | AF81: =IF(A_Entry_Forecast[[#This Row],[Target Price]]<>0,A_Entry_Forecast[[#This Row],[Target Price]]/AE81-1,"") -> 0.098650052 | AH81: HVN | AI81: 91458.545 | AJ81: -5807.1119 | AK81: -2622 | AL81: 0 | AM81: -0.0982 | AN81: 0.3801
B82: Phạm Thị Minh Châu | C82: FRT | D82: BUY | E82: 171300 | F82: 49315 | G82: 57754 | I82: 610 | J82: 865 | L82: 4481 | M82: 6350 | O82: 18520 | P82: 24878 | R82: 0.03 | S82: 0.04 | U82: 0.24 | V82: 0.26 | X82: =IF(OR(COUNTBLANK(A_Entry_Forecast[[#This Row],[REV_FY]])<>0,COUNTBLANK(A_Entry_Forecast[[#This Row],[REV_FY+1]])<>0),"N","Y") -> Y | AE82: =VLOOKUP(A_Entry_Forecast[[#This Row],[Ticker]],[1]!A_Entry_Data[#Data],2,FALSE) -> 150000 | AF82: =IF(A_Entry_Forecast[[#This Row],[Target Price]]<>0,A_Entry_Forecast[[#This Row],[Target Price]]/AE82-1,"") -> 0.142 | AH82: VJC | AI82: 62534.861 | AJ82: 343.04122 | AK82: 633 | AL82: 28823.86 | AM82: 0.0045 | AN82: 0.0226
B83: Phạm Thị Minh Châu | C83: MSN | D83: BUY | E83: 92700 | F83: 79506 | G83: 86215 | I83: 3435 | J83: 4216 | L83: 2270 | M83: 2787 | O83: 22258 | P83: 25042 | R83: 0.04 | S83: 0.05 | U83: 0.12 | V83: 0.14 | X83: =IF(OR(COUNTBLANK(A_Entry_Forecast[[#This Row],[REV_FY]])<>0,COUNTBLANK(A_Entry_Forecast[[#This Row],[REV_FY+1]])<>0),"N","Y") -> Y | AE83: =VLOOKUP(A_Entry_Forecast[[#This Row],[Ticker]],[1]!A_Entry_Data[#Data],2,FALSE) -> 83600 | AF83: =IF(A_Entry_Forecast[[#This Row],[Target Price]]<>0,A_Entry_Forecast[[#This Row],[Target Price]]/AE83-1,"") -> 0.10885167 | AH83: ELC | AI83: 980.08964 | AJ83: 77.13674 | AK83: 1294 | AL83: 11833.46 | AM83: 0.052 | AN83: 0.0905
B84: Phạm Thị Minh Châu | C84: MWG | D84: BUY | E84: 84700 | F84: 153559 | G84: 172781 | I84: 5800 | J84: 6841 | L84: 3909 | M84: 4611 | O84: 22026 | P84: 25670 | R84: 0.076 | S84: 0.081 | U84: 0.177 | V84: 0.18 | X84: =IF(OR(COUNTBLANK(A_Entry_Forecast[[#This Row],[REV_FY]])<>0,COUNTBLANK(A_Entry_Forecast[[#This Row],[REV_FY+1]])<>0),"N","Y") -> Y | AE84: =VLOOKUP(A_Entry_Forecast[[#This Row],[Ticker]],[1]!A_Entry_Data[#Data],2,FALSE) -> 72200 | AF84: =IF(A_Entry_Forecast[[#This Row],[Target Price]]<>0,A_Entry_Forecast[[#This Row],[Target Price]]/AE84-1,"") -> 0.17313019 | AH84: FPT | AI84: 52617.901 | AJ84: 6470.5224 | AK84: 4666 | AL84: 19677.77 | AM84: 0.1156 | AN84: 0.3385
B85: Phạm Thị Minh Châu | C85: PNJ | D85: HOLD | E85: 83000 | F85: 31700 | G85: 33514 | I85: 2074 | J85: 2229 | L85: 5532 | M85: 6072 | O85: 36614 | P85: 40695 | R85: 0.11 | S85: 0.11 | U85: 0.17 | V85: 0.17 | X85: =IF(OR(COUNTBLANK(A_Entry_Forecast[[#This Row],[REV_FY]])<>0,COUNTBLANK(A_Entry_Forecast[[#This Row],[REV_FY+1]])<>0),"N","Y") -> Y | AE85: =VLOOKUP(A_Entry_Forecast[[#This Row],[Ticker]],[1]!A_Entry_Data[#Data],2,FALSE) -> 87500 | AF85: =IF(A_Entry_Forecast[[#This Row],[Target Price]]<>0,A_Entry_Forecast[[#This Row],[Target Price]]/AE85-1,"") -> -0.051428571 | AH85: MSH | AI85: 4541.9076 | AJ85: 244.54961 | AK85: 3260 | AL85: 21947.78 | AM85: 0.0725 | AN85: 0.1507
B86: Phạm Thị Minh Châu | C86: VNM | D86: BUY | E86: 64600 | F86: 63188 | G86: 66202 | I86: 9144 | J86: 9597 | L86: 3916 | M86: 4110 | O86: 17911 | P86: 18543 | R86: 0.17 | S86: 0.17 | U86: 0.26 | V86: 0.25 | X86: =IF(OR(COUNTBLANK(A_Entry_Forecast[[#This Row],[REV_FY]])<>0,COUNTBLANK(A_Entry_Forecast[[#This Row],[REV_FY+1]])<>0),"N","Y") -> Y | AE86: 19300 | AF86: 0.19 | AH86: TNG | AI86: 7095.751 | AJ86: 225.68658 | AK86: 1988 | AL86: 0 | AM86: 0 | AN86: 0
B87: Trần Lâm Tùng | C87: HAH | D87: BUY | E87: 61700 | F87: 4727 | G87: 5196 | I87: 774 | J87: 891 | L87: 6379 | M87: 7340 | O87: 32179 | P87: 38775 | R87: 0.1 | S87: 0.1 | U87: 0.16 | V87: 0.15 | X87: =IF(OR(COUNTBLANK(A_Entry_Forecast[[#This Row],[REV_FY]])<>0,COUNTBLANK(A_Entry_Forecast[[#This Row],[REV_FY+1]])<>0),"N","Y") -> Y | Y87: 1233 | Z87: 2020 | AA87: 2282 | AB87: 1574 | AC87: 1603 | AD87: 806 | AE87: 22000 | AF87: 0.23 | AH87: VHC | AI87: 10038.577 | AJ87: 896.51565 | AK87: 4880 | AL87: 44509.8 | AM87: 0.0767 | AN87: 0.1198
B88: Trần Lâm Tùng | C88: ANV | D88: BUY | E88: 36000 | F88: 5928 | G88: 6474 | I88: 955 | J88: 1136 | L88: 3588 | M88: 4266 | O88: 13256 | P88: 16529 | R88: 0.17 | S88: 0.17 | U88: 0.26 | V88: 0.27 | X88: =IF(OR(COUNTBLANK(A_Entry_Forecast[[#This Row],[REV_FY]])<>0,COUNTBLANK(A_Entry_Forecast[[#This Row],[REV_FY+1]])<>0),"N","Y") -> Y | AE88: 64700
B89: Trần Lâm Tùng | C89: CTR | D89: HOLD | E89: 111000 | F89: 13957 | G89: 15684 | I89: 566 | J89: 762 | L89: 4948 | M89: 6659 | O89: 27219 | P89: 33878 | R89: 0.06 | S89: 0.08 | U89: 0.18 | V89: 0.2 | X89: =IF(OR(COUNTBLANK(A_Entry_Forecast[[#This Row],[REV_FY]])<>0,COUNTBLANK(A_Entry_Forecast[[#This Row],[REV_FY+1]])<>0),"N","Y") -> Y | AE89: 53000 | AF89: =IF(A_Entry_Forecast[[#This Row],[Target Price]]<>0,A_Entry_Forecast[[#This Row],[Target Price]]/AE89-1,"") -> 1.0943396 | AH89: C4G | AI89: 2624.15 | AJ89: 152.23422 | AK89: 530 | AL89: 10532.16 | AM89: 0.0169 | AN89: 0.0485
B90: Trần Lâm Tùng | C90: ELC | D90: BUY | E90: 28000 | F90: 1658 | G90: 1744 | I90: 143 | J90: 164 | L90: 1740 | M90: 1999 | O90: 17364 | P90: 19545 | R90: 0.06 | S90: 0.06 | U90: 0.1 | V90: 0.1 | X90: =IF(OR(COUNTBLANK(A_Entry_Forecast[[#This Row],[REV_FY]])<>0,COUNTBLANK(A_Entry_Forecast[[#This Row],[REV_FY+1]])<>0),"N","Y") -> Y | AE90: =VLOOKUP(A_Entry_Forecast[[#This Row],[Ticker]],[1]!A_Entry_Data[#Data],2,FALSE) -> 23650 | AF90: =IF(A_Entry_Forecast[[#This Row],[Target Price]]<>0,A_Entry_Forecast[[#This Row],[Target Price]]/AE90-1,"") -> 0.18393235 | AH90: CTD | AI90: 0 | AJ90: 0 | AK90: 0 | AL90: 0 | AM90: 0 | AN90: 0
B91: Trần Nguyên Tường Huy | C91: FPT | D91: HOLD | E91: 118700 | F91: 73267 | G91: 86654 | I91: 9332 | J91: 11219 | L91: 5042 | M91: 6061 | O91: 21041 | P91: 25579 | R91: 0.12 | S91: 0.12 | U91: 0.21 | V91: 0.21 | X91: =IF(OR(COUNTBLANK(A_Entry_Forecast[[#This Row],[REV_FY]])<>0,COUNTBLANK(A_Entry_Forecast[[#This Row],[REV_FY+1]])<>0),"N","Y") -> Y | AE91: 106400 | AF91: =IF(A_Entry_Forecast[[#This Row],[Target Price]]<>0,A_Entry_Forecast[[#This Row],[Target Price]]/AE91-1,"") -> 0.1156015 | AH91: FCN | AI91: 0 | AJ91: 0 | AK91: 0 | AL91: 0 | AM91: 0 | AN91: 0
B92: Trần Lâm Tùng | C92: MSH | D92: HOLD | E92: 50600 | F92: 5838 | G92: 6340 | I92: 440 | J92: 501 | L92: 5861 | M92: 6684 | O92: 29592 | P92: 32565 | R92: 0.11 | S92: 0.11 | U92: 0.2 | V92: 0.19 | X92: =IF(OR(COUNTBLANK(A_Entry_Forecast[[#This Row],[REV_FY]])<>0,COUNTBLANK(A_Entry_Forecast[[#This Row],[REV_FY+1]])<>0),"N","Y") -> Y | AE92: =VLOOKUP(A_Entry_Forecast[[#This Row],[Ticker]],[1]!A_Entry_Data[#Data],2,FALSE) -> 39000 | AF92: =IF(A_Entry_Forecast[[#This Row],[Target Price]]<>0,A_Entry_Forecast[[#This Row],[Target Price]]/AE92-1,"") -> 0.2974359 | AH92: GVR | AI92: 22079.89 | AJ92: 2585.2293 | AK92: 646 | AL92: 12426.25 | AM92: 0.033 | AN92: 0.0683
B93: Trần Lâm Tùng | C93: TNG | D93: HOLD | E93: 23900 | F93: 8350 | G93: 9177 | I93: 342 | J93: 378 | L93: 2812 | M93: 3104 | O93: 17259 | P93: 19132 | R93: 0.05 | S93: 0.05 | U93: 0.17455746 | V93: 0.15 | X93: =IF(OR(COUNTBLANK(A_Entry_Forecast[[#This Row],[REV_FY]])<>0,COUNTBLANK(A_Entry_Forecast[[#This Row],[REV_FY+1]])<>0),"N","Y") -> Y | AE93: =VLOOKUP(A_Entry_Forecast[[#This Row],[Ticker]],[1]!A_Entry_Data[#Data],2,FALSE) -> 22000 | AF93: =IF(A_Entry_Forecast[[#This Row],[Target Price]]<>0,A_Entry_Forecast[[#This Row],[Target Price]]/AE93-1,"") -> 0.086363636 | AH93: IDC | AI93: 7237.0318 | AJ93: 1392.9638 | AK93: 4221 | AL93: 15066.71 | AM93: 0.0802 | AN93: 0.3338
B94: Trần Lâm Tùng | C94: VHC | D94: HOLD | E94: 60000 | F94: 12518 | G94: 14226 | I94: 1250 | J94: 1477 | L94: 5682 | M94: 6713 | O94: 48739 | P94: 54571 | R94: 0.08 | S94: 0.09 | U94: 0.12 | V94: 0.12 | X94: =IF(OR(COUNTBLANK(A_Entry_Forecast[[#This Row],[REV_FY]])<>0,COUNTBLANK(A_Entry_Forecast[[#This Row],[REV_FY+1]])<>0),"N","Y") -> Y | AE94: =VLOOKUP(A_Entry_Forecast[[#This Row],[Ticker]],[1]!A_Entry_Data[#Data],2,FALSE) -> 59600 | AF94: =IF(A_Entry_Forecast[[#This Row],[Target Price]]<>0,A_Entry_Forecast[[#This Row],[Target Price]]/AE94-1,"") -> 0.0067114094 | AH94: LCG | AI94: 2030.5462 | AJ94: 120.4077 | AK94: 635 | AL94: 13125.56 | AM94: 0.0217 | AN94: 0.0469
B95: Trần Lâm Tùng | C95: HVN | D95: BUY | E95: 39000 | F95: 118364 | G95: 130924 | I95: 8956 | J95: 9505 | L95: 2873 | M95: 3236 | O95: 1230 | P95: 3179 | R95: 0.12 | S95: 0.12 | U95: n/a | V95: n/a | X95: =IF(OR(COUNTBLANK(A_Entry_Forecast[[#This Row],[REV_FY]])<>0,COUNTBLANK(A_Entry_Forecast[[#This Row],[REV_FY+1]])<>0),"N","Y") -> Y
B96: Trần Lâm Tùng | C96: PTB | D96: BUY | E96: 62706 | F96: 7123 | G96: 7767 | I96: 524 | J96: 583 | L96: 7838 | M96: 8712 | O96: 55667 | P96: 64433 | R96: 0.081215969 | S96: 0.08 | U96: 0.14 | V96: 0.14 | X96: =IF(OR(COUNTBLANK(A_Entry_Forecast[[#This Row],[REV_FY]])<>0,COUNTBLANK(A_Entry_Forecast[[#This Row],[REV_FY+1]])<>0),"N","Y") -> Y | AE96: =VLOOKUP(A_Entry_Forecast[[#This Row],[Ticker]],[1]!A_Entry_Data[#Data],2,FALSE) -> 55000 | AF96: =IF(A_Entry_Forecast[[#This Row],[Target Price]]<>0,A_Entry_Forecast[[#This Row],[Target Price]]/AE96-1,"") -> 0.14010909 | AH96: LHG | AI96: 394.85934 | AJ96: 166.46654 | AK96: 0 | AL96: 31890.56 | AM96: 0.0549 | AN96: 0.1064
B97: Trần Nguyên Tường Huy | C97: PVT | D97: HOLD | E97: 19100 | F97: 13352 | G97: 13545 | I97: 1071 | J97: 1121 | L97: 2119 | M97: 2207 | O97: 25830 | P97: 28653 | R97: 0.059 | S97: 0.057 | U97: 0.116 | V97: 0.105 | X97: =IF(OR(COUNTBLANK(A_Entry_Forecast[[#This Row],[REV_FY]])<>0,COUNTBLANK(A_Entry_Forecast[[#This Row],[REV_FY+1]])<>0),"N","Y") -> Y | AE97: 18800 | AF97: =IF(A_Entry_Forecast[[#This Row],[Target Price]]<>0,A_Entry_Forecast[[#This Row],[Target Price]]/AE97-1,"") -> 0.015957447 | AH97: PHR | AI97: 1351.0241 | AJ97: 622.15369 | AK97: 4592 | AL97: 26922.17 | AM97: 0.0996 | AN97: 0.1915
B98: Trần Nguyên Tường Huy | C98: GMD | D98: BUY | E98: 74900 | F98: 5166 | G98: 5636 | I98: 1452 | J98: 1545 | L98: 3458 | M98: 3678 | O98: 34618 | P98: 36923 | R98: 0.09 | S98: 0.1 | U98: 0.13 | V98: 0.13 | X98: =IF(OR(COUNTBLANK(A_Entry_Forecast[[#This Row],[REV_FY]])<>0,COUNTBLANK(A_Entry_Forecast[[#This Row],[REV_FY+1]])<>0),"N","Y") -> Y | AE98: 58900 | AF98: =IF(A_Entry_Forecast[[#This Row],[Target Price]]<>0,A_Entry_Forecast[[#This Row],[Target Price]]/AE98-1,"") -> 0.27164686 | AH98: SZC | AI98: 817.94562 | AJ98: 218.87329 | AK98: 1621 | AL98: 14477.63 | AM98: 0.0329 | AN98: 0.1338
B99: Vũ Công Hoàng Duy | C99: HT1 | D99: BUY | E99: 14300 | F99: 7189 | G99: 7631 | I99: 216 | J99: 306 | L99: 747 | M99: 1072 | O99: 13404 | P99: 13970 | R99: 0.02 | S99: 0.03 | U99: 0.04 | V99: 0.06 | X99: =IF(OR(COUNTBLANK(A_Entry_Forecast[[#This Row],[REV_FY]])<>0,COUNTBLANK(A_Entry_Forecast[[#This Row],[REV_FY+1]])<>0),"N","Y") -> Y | AE99: =VLOOKUP(A_Entry_Forecast[[#This Row],[Ticker]],[1]!A_Entry_Data[#Data],2,FALSE) -> 17150 | AF99: =IF(A_Entry_Forecast[[#This Row],[Target Price]]<>0,A_Entry_Forecast[[#This Row],[Target Price]]/AE99-1,"") -> -0.16618076 | AH99: SIP | AI99: 6673.4256 | AJ99: 956.23866 | AK99: 4695 | AL99: 19779.88 | AM99: 0.0477 | AN99: 0.3031
B100: Vũ Công Hoàng Duy | C100: LCG | D100: BUY | E100: 11500 | F100: 3219 | G100: 2292 | I100: 153 | J100: 62 | L100: 773 | M100: 321 | O100: 13672 | P100: 13734 | R100: 0.03 | S100: 0.02 | U100: 0.06 | V100: 0.02 | X100: =IF(OR(COUNTBLANK(A_Entry_Forecast[[#This Row],[REV_FY]])<>0,COUNTBLANK(A_Entry_Forecast[[#This Row],[REV_FY+1]])<>0),"N","Y") -> Y | AE100: =VLOOKUP(A_Entry_Forecast[[#This Row],[Ticker]],[1]!A_Entry_Data[#Data],2,FALSE) -> 11750 | AF100: =IF(A_Entry_Forecast[[#This Row],[Target Price]]<>0,A_Entry_Forecast[[#This Row],[Target Price]]/AE100-1,"") -> -0.021276596
B101: Vũ Công Hoàng Duy | C101: C4G | D101: HOLD | E101: 9600 | F101: 3288 | G101: 3376 | I101: 203 | J101: 209 | L101: 567 | M101: 585 | O101: 11543 | P101: 12126 | R101: 0.021 | S101: 0.021 | U101: 0.05 | V101: 0.049 | X101: =IF(OR(COUNTBLANK(A_Entry_Forecast[[#This Row],[REV_FY]])<>0,COUNTBLANK(A_Entry_Forecast[[#This Row],[REV_FY+1]])<>0),"N","Y") -> Y | AE101: =VLOOKUP(A_Entry_Forecast[[#This Row],[Ticker]],[1]!A_Entry_Data[#Data],2,FALSE) -> 9900 | AF101: =IF(A_Entry_Forecast[[#This Row],[Target Price]]<>0,A_Entry_Forecast[[#This Row],[Target Price]]/AE101-1,"") -> -0.03030303 | AJ101: 2023 | AK101: 2024
B102: Vũ Công Hoàng Duy | C102: HHV | D102: BUY | E102: 15600 | F102: 3494.3677 | G102: 3536.5317 | I102: 497.62231 | J102: 675.30407 | L102: 1151.2225 | M102: 1562.2798 | O102: 22518.842 | P102: 24286.442 | R102: 0.012850105 | S102: 0.017356808 | U102: 0.051122634 | V102: 0.06432724 | X102: =IF(OR(COUNTBLANK(A_Entry_Forecast[[#This Row],[REV_FY]])<>0,COUNTBLANK(A_Entry_Forecast[[#This Row],[REV_FY+1]])<>0),"N","Y") -> Y | AE102: =VLOOKUP(A_Entry_Forecast[[#This Row],[Ticker]],[1]!A_Entry_Data[#Data],2,FALSE) -> 15050 | AF102: =IF(A_Entry_Forecast[[#This Row],[Target Price]]<>0,A_Entry_Forecast[[#This Row],[Target Price]]/AE102-1,"") -> 0.03654485 | AH102: cảng | AJ102: 872.49092 | AK102: =SUM(#REF!,#REF!) -> #REF! | AL102: =AK102/AJ102-1 -> #REF!
B103: Phạm Quang Minh | C103: VCG | D103: BUY | E103: 26100 | F103: 14635 | G103: 17020 | I103: 885 | J103: 1218 | L103: 1478 | M103: 2035 | O103: 20023 | P103: 22022 | R103: 0.03 | S103: 0.04 | U103: 0.07 | V103: 0.09 | X103: =IF(OR(COUNTBLANK(A_Entry_Forecast[[#This Row],[REV_FY]])<>0,COUNTBLANK(A_Entry_Forecast[[#This Row],[REV_FY+1]])<>0),"N","Y") -> Y | AE103: =VLOOKUP(A_Entry_Forecast[[#This Row],[Ticker]],[1]!A_Entry_Data[#Data],2,FALSE) -> 26250 | AF103: =IF(A_Entry_Forecast[[#This Row],[Target Price]]<>0,A_Entry_Forecast[[#This Row],[Target Price]]/AE103-1,"") -> -0.0057142857
B104: Nguyễn Thị Cẩm Tú | C104: TCH | D104: NA | E104: 22400 | F104: 3963 | G104: 6617 | I104: 997 | J104: 2358 | L104: 1492 | M104: 3528 | O104: 15564 | P104: 18392 | R104: 0.066 | S104: 0.12 | U104: 0.082 | V104: 0.145 | X104: =IF(OR(COUNTBLANK(A_Entry_Forecast[[#This Row],[REV_FY]])<>0,COUNTBLANK(A_Entry_Forecast[[#This Row],[REV_FY+1]])<>0),"N","Y") -> Y | AE104: =VLOOKUP(A_Entry_Forecast[[#This Row],[Ticker]],[1]!A_Entry_Data[#Data],2,FALSE) -> 25350 | AF104: =IF(A_Entry_Forecast[[#This Row],[Target Price]]<>0,A_Entry_Forecast[[#This Row],[Target Price]]/AE104-1,"") -> -0.11637081
X108: =COUNTIF(A_Entry_Forecast[Forecast Y/N],"Y") -> 87
